{"AniPreSim":[{"Title":"平凡职业成就世界最强 第二季","Href":"/detail/20200169","NewTitle":"PV","AID":"20200169","PicSmall":"https://pic.rmb.bdstatic.com/bjh/a8badd1832d9f69be41c4bcd35740687.jpeg"},{"Title":"魔法少女奈叶 The MOVIE 2nd A's","Href":"/detail/20120089","NewTitle":"[全集]","AID":"20120089","PicSmall":"https://sc04.alicdn.com/kf/H03f6d25a0d894692a91099daa8bf91aaj.jpg"},{"Title":"天晴烂漫！","Href":"/detail/20200128","NewTitle":"[TV 01-13]","AID":"20200128","PicSmall":"https://sc04.alicdn.com/kf/H62828d28a6334f7fb8a1b718568007daS.jpg"},{"Title":"空罐少女","Href":"/detail/20090021","NewTitle":"[TV 01-12+OVA]","AID":"20090021","PicSmall":"https://sc04.alicdn.com/kf/H8187556abf15461587f4ddee791a64fat.jpg"},{"Title":"DOTA：龙之血","Href":"/detail/20210103","NewTitle":"第8集(完结)","AID":"20210103","PicSmall":"https://pic.rmb.bdstatic.com/bjh/ad3d662d59d85cf1fd8d47a5120b1a63.jpeg"},{"Title":"终结的炽天使 第二季","Href":"/detail/20150070","NewTitle":"[TV 13-24+SP+OVA]","AID":"20150070","PicSmall":"https://sc04.alicdn.com/kf/H7396f7e5e6344120b2c17f2870e6745bH.jpg"},{"Title":"织田信奈的野望","Href":"/detail/20120013","NewTitle":"[TV 01-13]","AID":"20120013","PicSmall":"https://sc04.alicdn.com/kf/Ha3d8aa6b0c7845d9b7aa8f1e3f1f010aI.jpg"},{"Title":"百花缭乱 SAMURAI AFTER","Href":"/detail/20150164","NewTitle":"[OVA 01-02]","AID":"20150164","PicSmall":"https://sc04.alicdn.com/kf/H3d0f0e62f6bf4eb49db7e2e884dbd46dv.jpg"}],"Tip":"AGE动漫网 备用地址：<a rel=\"nofollow\" target=\"_blank\" href=\"http://www.agefans.cc\" style=\"color: #60b8cc;text-decoration:  none;\">www.agefans.cc<\/a> 欢迎大家分享给身边朋友！为确保正常观看，请使用谷歌浏览器。","AniPreRel":[{"Title":"巴哈姆特之怒 GENESIS","Href":"/detail/20140020","NewTitle":"[TV 01-12]","AID":"20140020","PicSmall":"https://sc04.alicdn.com/kf/H3e3cc9a9b1ec465cbf97d5b5541f1b32t.jpg"},{"Title":"巴哈姆特之怒 GENESIS Short Story","Href":"/detail/20160034","NewTitle":"[OVA 01-02]","AID":"20160034","PicSmall":"https://sc04.alicdn.com/kf/H02a0bb880e1f4a74a9a7dfa8f0e8b48ew.jpg"},{"Title":"巴哈姆特之怒 VIRGIN SOUL","Href":"/detail/20170192","NewTitle":"[TV 01-24]","AID":"20170192","PicSmall":"https://sc04.alicdn.com/kf/H3d0641184a7442a19a8ccc95291d85cfs.jpg"},{"Title":"玛娜利亚魔法学院","Href":"/detail/20190075","NewTitle":"[TV 01-10]","AID":"20190075","PicSmall":"https://sc04.alicdn.com/kf/H25272aa47f01469498d7fe1f070378f8l.jpg"}],"AniInfo":{"CommentCnt":39,"R更新时间str2":"2017-06-11","R剧情类型2":["冒险","奇幻","神魔"],"R简介":"电视动画《巴哈姆特之怒GENESIS》改编自社交网络卡牌游戏《巴哈姆特之怒》，于2014年10月开始播放。\r\n这里是人、神、魔等种族共同生活的神秘世界，密斯塔尔希亚。过去，黑银之翼的巴哈姆特曾几乎令这个世界毁灭，但人，神，魔三族共同战斗，作出了巨大的牺牲后，终于把它的力量封印了起来。接着，神与魔两方分别保存着封印钥匙的一半。二千年以后，世界始终和平安宁。不知从什么时候起，人类将巴哈姆特当作了独一无二的尊贵存在，畏惧并崇拜它。某一天，一位少女夺走了保护严密的神族的钥匙。世界的均衡渐渐被打破。当巴哈姆特再次发出吼声之时，世界再次落入绝望的深渊。\u201c世界啊，毁灭吧！\u201d某个声音如此恳求着。","R其它名称":"神击的巴哈姆特 GENESIS","R地区":"日本","R在线播放":"","LastModified":"Sun, 6 Apr 2031 11:24:06 GMT","R更新时间str":"2017-06-11 00:07:14","R制作公司":"MAPPA","R标签2":["冒险","奇幻","神魔","战斗","剧情"],"ModifiedTime":1617852246,"R标题V2":"","R首播季度":"10","R更新时间":"20170611000714","DEF_PLAYINDEX":"1","R在线播放3":"第01话 [GB_CN][720p][MP4] <play>PC-WYD1<\/play>wyd-[KTXP][140020][01][GB_CN][720p][MP4] nvl.mp4\r\n第02话 [GB_CN][720p][MP4] <play>PC-WYD1<\/play>wyd-[KTXP][140020][02][GB_CN][720p][MP4] nvl.mp4\r\n第03话 [GB_CN][720p][MP4] <play>PC-WYD1<\/play>wyd-[KTXP][140020][03][GB_CN][720p][MP4] nvl.mp4\r\n第04话 [GB_CN][720p][MP4] <play>PC-WYD1<\/play>wyd-[KTXP][140020][04][GB_CN][720p][MP4] nvl.mp4\r\n第05话 [GB_CN][720p][MP4] <play>PC-WYD1<\/play>wyd-[KTXP][140020][05][GB_CN][720p][MP4] nvl.mp4\r\n第06话 ][GB_CN][720p][MP4] <play>PC-WYD1<\/play>wyd-[KTXP][140020][06)][GB_CN][720p][MP4] nvl.mp4\r\n第06.5话 [GB_CN][720p][MP4] <play>PC-WYD1<\/play>wyd-[KTXP][140020][06.5][GB_CN][720p][MP4] nvl.mp4\r\n第07话 [GB_CN][720p][MP4] <play>PC-WYD1<\/play>wyd-[KTXP][140020][07][GB_CN][720p][MP4] nvl.mp4\r\n第08话 [GB_CN][720p][MP4] <play>PC-WYD1<\/play>wyd-[KTXP][140020][08][GB_CN][720p][MP4] nvl.mp4\r\n第09话 [GB_CN][720p][MP4] <play>PC-WYD1<\/play>wyd-[KTXP][140020][09][GB_CN][720p][MP4] nvl.mp4\r\n第10话 [GB_CN][720p][MP4] <play>PC-WYD1<\/play>wyd-[KTXP][140020][10][GB_CN][720p][MP4] nvl.mp4\r\n第11话 [GB_CN][720p][MP4] <play>PC-WYD1<\/play>wyd-[KTXP][140020][11][GB_CN][720p][MP4] nvl.mp4\r\n第12话 [GB_CN][720p][MP4] <play>PC-WYD1<\/play>wyd-[KTXP][140020][12][GB_CN][720p][MP4] nvl.mp4","R在线播放2":"第01集 <play>web_m3u8<\/play>https%3a%2f%2fqiyi%2emhyunbo%2ecom%2f20191005%2fwLKs9mJH%2findex%2em3u8\r\n第02集 <play>web_m3u8<\/play>https%3a%2f%2fqiyi%2emhyunbo%2ecom%2f20191005%2fjg8FkrxZ%2findex%2em3u8\r\n第03集 <play>web_m3u8<\/play>https%3a%2f%2fqiyi%2emhyunbo%2ecom%2f20191005%2fFmBHFapY%2findex%2em3u8\r\n第04集 <play>web_m3u8<\/play>https%3a%2f%2fqiyi%2emhyunbo%2ecom%2f20191005%2fe1CyKfBH%2findex%2em3u8\r\n第05集 <play>web_m3u8<\/play>https%3a%2f%2fqiyi%2emhyunbo%2ecom%2f20191005%2f3JeHIxua%2findex%2em3u8\r\n第06集 <play>web_m3u8<\/play>https%3a%2f%2fqiyi%2emhyunbo%2ecom%2f20191005%2fl4JbzKVB%2findex%2em3u8\r\n第6.5集 <play>web_m3u8<\/play>https%3a%2f%2fqiyi%2emhyunbo%2ecom%2f20191005%2f8gdhzJB8%2findex%2em3u8\r\n第07集 <play>web_m3u8<\/play>https%3a%2f%2fqiyi%2emhyunbo%2ecom%2f20191005%2fbqVYjNo8%2findex%2em3u8\r\n第08集 <play>web_m3u8<\/play>https%3a%2f%2fqiyi%2emhyunbo%2ecom%2f20191005%2fBu9hW95x%2findex%2em3u8\r\n第09集 <play>web_m3u8<\/play>https%3a%2f%2fqiyi%2emhyunbo%2ecom%2f20191005%2fSZDTtTTF%2findex%2em3u8\r\n第10集 <play>web_m3u8<\/play>https%3a%2f%2fqiyi%2emhyunbo%2ecom%2f20191005%2ff4TaP572%2findex%2em3u8\r\n第11集 <play>web_m3u8<\/play>https%3a%2f%2fqiyi%2emhyunbo%2ecom%2f20191005%2fakZL6M2d%2findex%2em3u8\r\n第12集 <play>web_m3u8<\/play>https%3a%2f%2fqiyi%2emhyunbo%2ecom%2f20191005%2fwT25t6HE%2findex%2em3u8","R封面图":"https://sc04.alicdn.com/kf/H41df9021d06044949d5e45e120074a88H.jpg","R在线播放4":"第01话 [GB_CN][720p][MP4] <play>PC-QUNS<\/play>quns-[KTXP][Shingeki no Bahamut GENESIS][01][GB_CN][720p][MP4]-remux nvl-fs.zip\r\n第02话 [GB_CN][720p][MP4] <play>PC-QUNS<\/play>quns-[KTXP][Shingeki no Bahamut GENESIS][02][GB_CN][720p][MP4]-remux nvl-fs.zip\r\n第03话 [GB_CN][720p][MP4] <play>PC-QUNS<\/play>quns-[KTXP][Shingeki no Bahamut GENESIS][03][GB_CN][720p][MP4]-remux nvl-fs.zip\r\n第04话 [GB_CN][720p][MP4] <play>PC-QUNS<\/play>quns-[KTXP][Shingeki no Bahamut GENESIS][04][GB_CN][720p][MP4]-remux nvl-fs.zip\r\n第05话 [GB_CN][720p][MP4] <play>PC-QUNS<\/play>quns-[KTXP][Shingeki no Bahamut GENESIS][05][GB_CN][720p][MP4]-remux nvl-fs.zip\r\n第06.5话 [GB_CN][720p][MP4] <play>PC-QUNS<\/play>quns-[KTXP][Shingeki no Bahamut GENESIS][06.5][GB_CN][720p][MP4]-remux nvl-fs.zip\r\n第06话 ][GB_CN][720p][MP4] <play>PC-QUNS<\/play>quns-[KTXP][Shingeki no Bahamut GENESIS][06)][GB_CN][720p][MP4]-remux nvl-fs.zip\r\n第07话 [GB_CN][720p][MP4] <play>PC-QUNS<\/play>quns-[KTXP][Shingeki no Bahamut GENESIS][07][GB_CN][720p][MP4]-remux nvl-fs.zip\r\n第08话 [GB_CN][720p][MP4] <play>PC-QUNS<\/play>quns-[KTXP][Shingeki no Bahamut GENESIS][08][GB_CN][720p][MP4]-remux nvl-fs.zip\r\n第09话 [GB_CN][720p][MP4] <play>PC-QUNS<\/play>quns-[KTXP][Shingeki no Bahamut GENESIS][09][GB_CN][720p][MP4]-remux nvl-fs.zip\r\n第10话 [GB_CN][720p][MP4] <play>PC-QUNS<\/play>quns-[KTXP][Shingeki no Bahamut GENESIS][10][GB_CN][720p][MP4]-remux nvl-fs.zip\r\n第11话 [GB_CN][720p][MP4] <play>PC-QUNS<\/play>quns-[KTXP][Shingeki no Bahamut GENESIS][11][GB_CN][720p][MP4]-remux nvl-fs.zip\r\n第12话 [GB_CN][720p][MP4] <play>PC-QUNS<\/play>quns-[KTXP][Shingeki no Bahamut GENESIS][12][GB_CN][720p][MP4]-remux nvl-fs.zip","AID":"20140020","R系列":"巴哈姆特之怒","R播放状态":"完结","R备用":"rbak","R原版名称":"神撃のバハムート GENESIS","R原作":"Cygames","R简介_br":"电视动画《巴哈姆特之怒GENESIS》改编自社交网络卡牌游戏《巴哈姆特之怒》，于2014年10月开始播放。<br/>这里是人、神、魔等种族共同生活的神秘世界，密斯塔尔希亚。过去，黑银之翼的巴哈姆特曾几乎令这个世界毁灭，但人，神，魔三族共同战斗，作出了巨大的牺牲后，终于把它的力量封印了起来。接着，神与魔两方分别保存着封印钥匙的一半。二千年以后，世界始终和平安宁。不知从什么时候起，人类将巴哈姆特当作了独一无二的尊贵存在，畏惧并崇拜它。某一天，一位少女夺走了保护严密的神族的钥匙。世界的均衡渐渐被打破。当巴哈姆特再次发出吼声之时，世界再次落入绝望的深渊。\u201c世界啊，毁灭吧！\u201d某个声音如此恳求着。","R在线播放All":[[],[{"PlayVid":"https%3a%2f%2fqiyi%2emhyunbo%2ecom%2f20191005%2fwLKs9mJH%2findex%2em3u8","Ex":"","Title_l":"第01集","Title":"第01集","EpName":"1","PlayId":"<play>web_m3u8<\/play>","EpPic":""},{"PlayVid":"https%3a%2f%2fqiyi%2emhyunbo%2ecom%2f20191005%2fjg8FkrxZ%2findex%2em3u8","Ex":"","Title_l":"第02集","Title":"第02集","EpName":"2","PlayId":"<play>web_m3u8<\/play>","EpPic":""},{"PlayVid":"https%3a%2f%2fqiyi%2emhyunbo%2ecom%2f20191005%2fFmBHFapY%2findex%2em3u8","Ex":"","Title_l":"第03集","Title":"第03集","EpName":"3","PlayId":"<play>web_m3u8<\/play>","EpPic":""},{"PlayVid":"https%3a%2f%2fqiyi%2emhyunbo%2ecom%2f20191005%2fe1CyKfBH%2findex%2em3u8","Ex":"","Title_l":"第04集","Title":"第04集","EpName":"4","PlayId":"<play>web_m3u8<\/play>","EpPic":""},{"PlayVid":"https%3a%2f%2fqiyi%2emhyunbo%2ecom%2f20191005%2f3JeHIxua%2findex%2em3u8","Ex":"","Title_l":"第05集","Title":"第05集","EpName":"5","PlayId":"<play>web_m3u8<\/play>","EpPic":""},{"PlayVid":"https%3a%2f%2fqiyi%2emhyunbo%2ecom%2f20191005%2fl4JbzKVB%2findex%2em3u8","Ex":"","Title_l":"第06集","Title":"第06集","EpName":"6","PlayId":"<play>web_m3u8<\/play>","EpPic":""},{"PlayVid":"https%3a%2f%2fqiyi%2emhyunbo%2ecom%2f20191005%2f8gdhzJB8%2findex%2em3u8","Ex":"","Title_l":"第6.5集","Title":"第6.5集","EpName":"6.5","PlayId":"<play>web_m3u8<\/play>","EpPic":""},{"PlayVid":"https%3a%2f%2fqiyi%2emhyunbo%2ecom%2f20191005%2fbqVYjNo8%2findex%2em3u8","Ex":"","Title_l":"第07集","Title":"第07集","EpName":"7","PlayId":"<play>web_m3u8<\/play>","EpPic":""},{"PlayVid":"https%3a%2f%2fqiyi%2emhyunbo%2ecom%2f20191005%2fBu9hW95x%2findex%2em3u8","Ex":"","Title_l":"第08集","Title":"第08集","EpName":"8","PlayId":"<play>web_m3u8<\/play>","EpPic":""},{"PlayVid":"https%3a%2f%2fqiyi%2emhyunbo%2ecom%2f20191005%2fSZDTtTTF%2findex%2em3u8","Ex":"","Title_l":"第09集","Title":"第09集","EpName":"9","PlayId":"<play>web_m3u8<\/play>","EpPic":""},{"PlayVid":"https%3a%2f%2fqiyi%2emhyunbo%2ecom%2f20191005%2ff4TaP572%2findex%2em3u8","Ex":"","Title_l":"第10集","Title":"第10集","EpName":"10","PlayId":"<play>web_m3u8<\/play>","EpPic":""},{"PlayVid":"https%3a%2f%2fqiyi%2emhyunbo%2ecom%2f20191005%2fakZL6M2d%2findex%2em3u8","Ex":"","Title_l":"第11集","Title":"第11集","EpName":"11","PlayId":"<play>web_m3u8<\/play>","EpPic":""},{"PlayVid":"https%3a%2f%2fqiyi%2emhyunbo%2ecom%2f20191005%2fwT25t6HE%2findex%2em3u8","Ex":"","Title_l":"第12集","Title":"第12集","EpName":"12","PlayId":"<play>web_m3u8<\/play>","EpPic":""}],[{"PlayVid":"wyd-[KTXP][140020][01][GB_CN][720p][MP4] nvl.mp4","Ex":"","Title_l":"第01话 [GB_CN][720p][MP4]","Title":"第01话","EpName":"1","PlayId":"<play>PC-WYD1<\/play>","EpPic":""},{"PlayVid":"wyd-[KTXP][140020][02][GB_CN][720p][MP4] nvl.mp4","Ex":"","Title_l":"第02话 [GB_CN][720p][MP4]","Title":"第02话","EpName":"2","PlayId":"<play>PC-WYD1<\/play>","EpPic":""},{"PlayVid":"wyd-[KTXP][140020][03][GB_CN][720p][MP4] nvl.mp4","Ex":"","Title_l":"第03话 [GB_CN][720p][MP4]","Title":"第03话","EpName":"3","PlayId":"<play>PC-WYD1<\/play>","EpPic":""},{"PlayVid":"wyd-[KTXP][140020][04][GB_CN][720p][MP4] nvl.mp4","Ex":"","Title_l":"第04话 [GB_CN][720p][MP4]","Title":"第04话","EpName":"4","PlayId":"<play>PC-WYD1<\/play>","EpPic":""},{"PlayVid":"wyd-[KTXP][140020][05][GB_CN][720p][MP4] nvl.mp4","Ex":"","Title_l":"第05话 [GB_CN][720p][MP4]","Title":"第05话","EpName":"5","PlayId":"<play>PC-WYD1<\/play>","EpPic":""},{"PlayVid":"wyd-[KTXP][140020][06)][GB_CN][720p][MP4] nvl.mp4","Ex":"","Title_l":"第06话 ][GB_CN][720p][MP4]","Title":"第06话","EpName":"6","PlayId":"<play>PC-WYD1<\/play>","EpPic":""},{"PlayVid":"wyd-[KTXP][140020][06.5][GB_CN][720p][MP4] nvl.mp4","Ex":"","Title_l":"第06.5话 [GB_CN][720p][MP4]","Title":"第06.5话","EpName":"6.5","PlayId":"<play>PC-WYD1<\/play>","EpPic":""},{"PlayVid":"wyd-[KTXP][140020][07][GB_CN][720p][MP4] nvl.mp4","Ex":"","Title_l":"第07话 [GB_CN][720p][MP4]","Title":"第07话","EpName":"7","PlayId":"<play>PC-WYD1<\/play>","EpPic":""},{"PlayVid":"wyd-[KTXP][140020][08][GB_CN][720p][MP4] nvl.mp4","Ex":"","Title_l":"第08话 [GB_CN][720p][MP4]","Title":"第08话","EpName":"8","PlayId":"<play>PC-WYD1<\/play>","EpPic":""},{"PlayVid":"wyd-[KTXP][140020][09][GB_CN][720p][MP4] nvl.mp4","Ex":"","Title_l":"第09话 [GB_CN][720p][MP4]","Title":"第09话","EpName":"9","PlayId":"<play>PC-WYD1<\/play>","EpPic":""},{"PlayVid":"wyd-[KTXP][140020][10][GB_CN][720p][MP4] nvl.mp4","Ex":"","Title_l":"第10话 [GB_CN][720p][MP4]","Title":"第10话","EpName":"10","PlayId":"<play>PC-WYD1<\/play>","EpPic":""},{"PlayVid":"wyd-[KTXP][140020][11][GB_CN][720p][MP4] nvl.mp4","Ex":"","Title_l":"第11话 [GB_CN][720p][MP4]","Title":"第11话","EpName":"11","PlayId":"<play>PC-WYD1<\/play>","EpPic":""},{"PlayVid":"wyd-[KTXP][140020][12][GB_CN][720p][MP4] nvl.mp4","Ex":"","Title_l":"第12话 [GB_CN][720p][MP4]","Title":"第12话","EpName":"12","PlayId":"<play>PC-WYD1<\/play>","EpPic":""}],[{"PlayVid":"quns-[KTXP][Shingeki no Bahamut GENESIS][01][GB_CN][720p][MP4]-remux nvl-fs.zip","Ex":"","Title_l":"第01话 [GB_CN][720p][MP4]","Title":"第01话","EpName":"1","PlayId":"<play>PC-QUNS<\/play>","EpPic":""},{"PlayVid":"quns-[KTXP][Shingeki no Bahamut GENESIS][02][GB_CN][720p][MP4]-remux nvl-fs.zip","Ex":"","Title_l":"第02话 [GB_CN][720p][MP4]","Title":"第02话","EpName":"2","PlayId":"<play>PC-QUNS<\/play>","EpPic":""},{"PlayVid":"quns-[KTXP][Shingeki no Bahamut GENESIS][03][GB_CN][720p][MP4]-remux nvl-fs.zip","Ex":"","Title_l":"第03话 [GB_CN][720p][MP4]","Title":"第03话","EpName":"3","PlayId":"<play>PC-QUNS<\/play>","EpPic":""},{"PlayVid":"quns-[KTXP][Shingeki no Bahamut GENESIS][04][GB_CN][720p][MP4]-remux nvl-fs.zip","Ex":"","Title_l":"第04话 [GB_CN][720p][MP4]","Title":"第04话","EpName":"4","PlayId":"<play>PC-QUNS<\/play>","EpPic":""},{"PlayVid":"quns-[KTXP][Shingeki no Bahamut GENESIS][05][GB_CN][720p][MP4]-remux nvl-fs.zip","Ex":"","Title_l":"第05话 [GB_CN][720p][MP4]","Title":"第05话","EpName":"5","PlayId":"<play>PC-QUNS<\/play>","EpPic":""},{"PlayVid":"quns-[KTXP][Shingeki no Bahamut GENESIS][06.5][GB_CN][720p][MP4]-remux nvl-fs.zip","Ex":"","Title_l":"第06.5话 [GB_CN][720p][MP4]","Title":"第06.5话","EpName":"6.5","PlayId":"<play>PC-QUNS<\/play>","EpPic":""},{"PlayVid":"quns-[KTXP][Shingeki no Bahamut GENESIS][06)][GB_CN][720p][MP4]-remux nvl-fs.zip","Ex":"","Title_l":"第06话 ][GB_CN][720p][MP4]","Title":"第06话","EpName":"6","PlayId":"<play>PC-QUNS<\/play>","EpPic":""},{"PlayVid":"quns-[KTXP][Shingeki no Bahamut GENESIS][07][GB_CN][720p][MP4]-remux nvl-fs.zip","Ex":"","Title_l":"第07话 [GB_CN][720p][MP4]","Title":"第07话","EpName":"7","PlayId":"<play>PC-QUNS<\/play>","EpPic":""},{"PlayVid":"quns-[KTXP][Shingeki no Bahamut GENESIS][08][GB_CN][720p][MP4]-remux nvl-fs.zip","Ex":"","Title_l":"第08话 [GB_CN][720p][MP4]","Title":"第08话","EpName":"8","PlayId":"<play>PC-QUNS<\/play>","EpPic":""},{"PlayVid":"quns-[KTXP][Shingeki no Bahamut GENESIS][09][GB_CN][720p][MP4]-remux nvl-fs.zip","Ex":"","Title_l":"第09话 [GB_CN][720p][MP4]","Title":"第09话","EpName":"9","PlayId":"<play>PC-QUNS<\/play>","EpPic":""},{"PlayVid":"quns-[KTXP][Shingeki no Bahamut GENESIS][10][GB_CN][720p][MP4]-remux nvl-fs.zip","Ex":"","Title_l":"第10话 [GB_CN][720p][MP4]","Title":"第10话","EpName":"10","PlayId":"<play>PC-QUNS<\/play>","EpPic":""},{"PlayVid":"quns-[KTXP][Shingeki no Bahamut GENESIS][11][GB_CN][720p][MP4]-remux nvl-fs.zip","Ex":"","Title_l":"第11话 [GB_CN][720p][MP4]","Title":"第11话","EpName":"11","PlayId":"<play>PC-QUNS<\/play>","EpPic":""},{"PlayVid":"quns-[KTXP][Shingeki no Bahamut GENESIS][12][GB_CN][720p][MP4]-remux nvl-fs.zip","Ex":"","Title_l":"第12话 [GB_CN][720p][MP4]","Title":"第12话","EpName":"12","PlayId":"<play>PC-QUNS<\/play>","EpPic":""}]],"R资源类型":"","R标签":"冒险 奇幻 神魔 战斗 剧情","R推荐星级":3,"R首播年份":"2014","R动画种类":"TV","R官方网站":"http://shingekinobahamut-genesis.jp/","R动画名称":"巴哈姆特之怒 GENESIS","R更新时间unix":1497110834,"R剧情类型":"冒险 奇幻 神魔","R字母索引":"B","R网盘资源":"[TV 01-12 720P]\\n 链接：https://pan.baidu.com/s/1ysaNzhZ0F-jW7J64x4f44g 密码：ae7b","R视频尺寸":"720P/1080P","RankCnt":67899,"CollectCnt":496,"R首播时间":"2014-10-06","R网盘资源2":[{"Title":"[TV 01-12 720P]","ExCode":"ae7b","Link":"https://pan.baidu.com/s/1ysaNzhZ0F-jW7J64x4f44g"}],"R封面图小":"https://sc04.alicdn.com/kf/H3e3cc9a9b1ec465cbf97d5b5541f1b32t.jpg","R新番标题":"[TV 01-12]"}}