{"AniInfo":{"AID":"20150094","R地区":"日本","R动画种类":"OVA","R动画名称":"魔鬼恋人OAD","R原版名称":"DIABOLIK LOVERS OAD","R其它名称":"暂无","R字母索引":"M","R原作":"オトメイト","R制作公司":"ZEXCS","R首播时间":"2015-02-26","R播放状态":"完结","R剧情类型":"爱情 女性向 吸血鬼","R在线播放":"","R在线播放2":"OAD01 [576P][CHS] <play>tieba<\/play>607272_8902f5b9ee380f9bd1d3adff6eb8d9c0.mp4","R在线播放3":"OAD01 <play>PPTV接口<\/play>\/\/v.pptv.com\/show\/Zyto5yUzKmjLSbE.html?rcc_src=B3","R在线播放4":"","R新番标题":"[OAD全集]","R网盘资源":"[OAD全集 576P]\\n 链接：https:\/\/pan.baidu.com\/s\/107dLKZSH75rju18wPmI_Vg 密码：15a8","R视频尺寸":"720P\/1080P","R资源类型":"","R备用":"rbak","R系列":"魔鬼恋人","R官方网站":"暂无","R标签":"爱情 女性向 吸血鬼","R更新时间":"20170702233341","R标题V2":"","R推荐星级":2,"R封面图":"https:\/\/sc04.alicdn.com\/kf\/Hbc74335fc5e24562b9b4d6e5aaa94fbfm.jpg","R封面图小":"https:\/\/sc04.alicdn.com\/kf\/H387b79bb12694131b9237ecbb0f93f36t.jpg","R简介":"魔鬼恋人OAD将在明年发售的PSV平台游戏「DIABOLIK LOVERS DARK FATE」的animate限定套装中收录新作OVA的DVD。","DEF_PLAYINDEX":"1","R更新时间unix":1499009621,"R更新时间str":"2017-07-02 23:33:41","R更新时间str2":"2017-07-02","R简介_br":"魔鬼恋人OAD将在明年发售的PSV平台游戏「DIABOLIK LOVERS DARK FATE」的animate限定套装中收录新作OVA的DVD。","R标签2":["爱情","女性向","吸血鬼"],"R剧情类型2":["爱情","女性向","吸血鬼"],"R在线播放All":[[],[{"Title":"OAD01","Title_l":"OAD01 [576P][CHS]","PlayId":"<play>tieba<\/play>","PlayVid":"607272_8902f5b9ee380f9bd1d3adff6eb8d9c0.mp4","EpName":"OAD01","EpPic":"","Ex":""}],[{"Title":"OAD01","Title_l":"OAD01","PlayId":"<play>PPTV接口<\/play>","PlayVid":"\/\/v.pptv.com\/show\/Zyto5yUzKmjLSbE.html?rcc_src=B3","EpName":"OAD01","EpPic":"","Ex":""}],[]],"R网盘资源2":[{"Title":"[OAD全集 576P]","Link":"https:\/\/pan.baidu.com\/s\/107dLKZSH75rju18wPmI_Vg","ExCode":"15a8"}],"R首播年份":"2015","R首播季度":"1","RankCnt":13342,"CommentCnt":12,"CollectCnt":74,"ModifiedTime":1614072428,"LastModified":"Fri, 21 Feb 2031 17:27:08 GMT"},"AniPreRel":[{"AID":"20130041","Title":"魔鬼恋人","NewTitle":"[TV 01-12]","PicSmall":"https:\/\/sc04.alicdn.com\/kf\/Hf76a758c84344a7e8e2aadccc0751653J.jpg","Href":"\/detail\/20130041"},{"AID":"20150093","Title":"魔鬼恋人 第二季","NewTitle":"[TV 01-12]","PicSmall":"https:\/\/sc04.alicdn.com\/kf\/Haf4bc3732f1e48b5b68a5b9d26e46f92F.jpg","Href":"\/detail\/20150093"},{"AID":"20150094","Title":"魔鬼恋人OAD","NewTitle":"[OAD全集]","PicSmall":"https:\/\/sc04.alicdn.com\/kf\/H387b79bb12694131b9237ecbb0f93f36t.jpg","Href":"\/detail\/20150094"}],"AniPreSim":[{"AID":"20190044","Title":"明治东京恋伽","NewTitle":"[TV 01-12]","PicSmall":"https:\/\/sc04.alicdn.com\/kf\/H34e6a1de8ed74a7bae958b1c1ddacad7M.jpg","Href":"\/detail\/20190044"},{"AID":"20180113","Title":"Butlers～千年百年物语～","NewTitle":"[TV 01-12+OVA]","PicSmall":"https:\/\/sc04.alicdn.com\/kf\/Hecec024cd5474c8b91b381ef0390bbf0n.jpg","Href":"\/detail\/20180113"},{"AID":"20130071","Title":"AMNESIA失忆症","NewTitle":"[TV 01-12+OVA]","PicSmall":"https:\/\/sc04.alicdn.com\/kf\/H2b9a47f854204981b5478ed3aacd6832M.jpg","Href":"\/detail\/20130071"},{"AID":"20140098","Title":"青春之旅","NewTitle":"[TV 01-12+OAD]","PicSmall":"https:\/\/sc04.alicdn.com\/kf\/Hf6a519ad17834cf9a2ca35eb65256225a.jpg","Href":"\/detail\/20140098"},{"AID":"20150090","Title":"元气少女缘结神 第二季","NewTitle":"[TV 01-12]","PicSmall":"https:\/\/sc04.alicdn.com\/kf\/H7ad1dba0eb9b45a3a50ffa47cea92d31t.jpg","Href":"\/detail\/20150090"},{"AID":"20180060","Title":"废柴王子","NewTitle":"[TV 01-12]","PicSmall":"https:\/\/sc04.alicdn.com\/kf\/Hed5cb555eeec4e99bba40cf17f4b8edfM.jpg","Href":"\/detail\/20180060"},{"AID":"20140093","Title":"尽管如此世界依然美丽","NewTitle":"[TV 01-12]","PicSmall":"https:\/\/sc04.alicdn.com\/kf\/H78408336bf7a487090cb8ef7e98eab826.jpg","Href":"\/detail\/20140093"},{"AID":"20120023","Title":"元气少女缘结神","NewTitle":"[TV 01-13]","PicSmall":"https:\/\/sc04.alicdn.com\/kf\/Hf66afd02ac3c4d8e9172d6d1db562d786.jpg","Href":"\/detail\/20120023"}],"Tip":"AGE动漫网 备用地址：<a rel=\"nofollow\" target=\"_blank\" href=\"http:\/\/www.agefans.cc\" style=\"color: #60b8cc;text-decoration:  none;\">www.agefans.cc<\/a> 欢迎大家分享给身边朋友！为确保正常观看，请使用谷歌浏览器。"}