{"AniPreSim":[{"Title":"PROMARE","Href":"/detail/20190087","NewTitle":"[全集]","AID":"20190087","PicSmall":"https://sc04.alicdn.com/kf/Hfb3b5bd8a31446fcb97425f2adeedbb6T.jpg"},{"Title":"剑姬神圣谭","Href":"/detail/20170037","NewTitle":"[TV 01-12]","AID":"20170037","PicSmall":"https://sc04.alicdn.com/kf/H55f8fb58219540eeb01586e39cc900a3W.jpg"},{"Title":"K","Href":"/detail/20120036","NewTitle":"[TV 01-13]","AID":"20120036","PicSmall":"https://sc04.alicdn.com/kf/H3c41d078b3234f5c9a509df7a24b0ee7F.jpg"},{"Title":"烟草","Href":"/detail/20190099","NewTitle":"[TV 01-12]","AID":"20190099","PicSmall":"https://sc04.alicdn.com/kf/Ha59552a6f791426583a6551b92ab7d4cS.jpg"},{"Title":"血界战线 第二季","Href":"/detail/20170109","NewTitle":"[TV 01-12]","AID":"20170109","PicSmall":"https://sc04.alicdn.com/kf/Ha71f65306c4840399c18591efe0be077U.jpg"},{"Title":"圣剑锻造师","Href":"/detail/20090009","NewTitle":"[BD 01-12]","AID":"20090009","PicSmall":"https://sc04.alicdn.com/kf/Hf7cfa353a60746b1b543bc94bc70cd3cm.jpg"},{"Title":"食神魂 第二季","Href":"/detail/20180067","NewTitle":"[TV 01-12]","AID":"20180067","PicSmall":"https://sc04.alicdn.com/kf/Hef41c946628745908b9c1fc152e083e14.jpg"},{"Title":"关于我转生变成史莱姆这档事","Href":"/detail/20180220","NewTitle":"[TV 01-24.5]","AID":"20180220","PicSmall":"https://sc04.alicdn.com/kf/He5ba0ae821c34ec5a2c29823ad80e23a8.jpg"}],"Tip":"AGE动漫网 备用地址：<a rel=\"nofollow\" target=\"_blank\" href=\"http://www.agefans.cc\" style=\"color: #60b8cc;text-decoration:  none;\">www.agefans.cc<\/a> 欢迎大家分享给身边朋友！为确保正常观看，请使用谷歌浏览器。","AniPreRel":[{"Title":"妖神记","Href":"/detail/20170163","NewTitle":"第40话(完结)","AID":"20170163","PicSmall":"https://sc04.alicdn.com/kf/H9d656696a20346beb17200e09549c239a.jpg"},{"Title":"妖神记 第二季","Href":"/detail/20180349","NewTitle":"第80集(完结)","AID":"20180349","PicSmall":"https://sc04.alicdn.com/kf/H599d254af50745e6ab6c486697fce32at.jpg"},{"Title":"妖神记之影妖篇","Href":"/detail/20180350","NewTitle":"第40集(完结)","AID":"20180350","PicSmall":"https://sc04.alicdn.com/kf/Hd71c2b8048d349afb4e1805b1cf0a8f37.jpg"},{"Title":"妖神记之黑狱篇","Href":"/detail/20200193","NewTitle":"第52集(完结)","AID":"20200193","PicSmall":"https://sc04.alicdn.com/kf/H6bcb473d85d1416c8d7b2871137436b42.jpg"}],"AniInfo":{"CommentCnt":4,"R更新时间str2":"2019-04-08","R剧情类型2":["热血","冒险","战斗"],"R简介":"神秘瑰丽的妖灵世界，奇奥无穷的时空妖灵之书，聂离追寻着世界的真相。美丽温柔的叶紫芸、倔强高傲的肖凝儿，面对两位女神的青睐，他该如何抉择？还有患难与共的兄弟，一起修炼最强功法、最强妖灵之力，踏足武道巅峰。","R其它名称":"暂无","R地区":"中国","R在线播放":"","LastModified":"Mon, 7 Apr 2031 08:31:16 GMT","R更新时间str":"2019-04-08 13:50:28","R制作公司":"若鸿文化","R标签2":["热血","冒险","战斗"],"ModifiedTime":1617928276,"R标题V2":"","R首播季度":"1","R更新时间":"20190408135028","DEF_PLAYINDEX":"1","R在线播放3":"第1集 <play>web_m3u8<\/play>https%3a%2f%2f2%2emhbobo%2ecom%2f20190905%2fFuhHYM8F%2findex%2em3u8\r\n第2集 <play>web_m3u8<\/play>https%3a%2f%2f2%2emhbobo%2ecom%2f20190905%2fwxPwauSL%2findex%2em3u8\r\n第3集 <play>web_m3u8<\/play>https%3a%2f%2f2%2emhbobo%2ecom%2f20190905%2fYbUpQjqV%2findex%2em3u8\r\n第4集 <play>web_m3u8<\/play>https%3a%2f%2f2%2emhbobo%2ecom%2f20190905%2f5bxHxGhQ%2findex%2em3u8\r\n第5集 <play>web_m3u8<\/play>https%3a%2f%2f2%2emhbobo%2ecom%2f20190905%2f4fQgUbCc%2findex%2em3u8\r\n第6集 <play>web_m3u8<\/play>https%3a%2f%2f2%2emhbobo%2ecom%2f20190905%2fHrN2o89e%2findex%2em3u8\r\n第7集 <play>web_m3u8<\/play>https%3a%2f%2f2%2emhbobo%2ecom%2f20190905%2f7SjZr6G3%2findex%2em3u8\r\n第8集 <play>web_m3u8<\/play>https%3a%2f%2f2%2emhbobo%2ecom%2f20190905%2f6xLQZ9yB%2findex%2em3u8\r\n第9集 <play>web_m3u8<\/play>https%3a%2f%2f2%2emhbobo%2ecom%2f20190905%2fv14bZ3KF%2findex%2em3u8\r\n第10集 <play>web_m3u8<\/play>https%3a%2f%2f2%2emhbobo%2ecom%2f20190905%2fzuhSjjvK%2findex%2em3u8\r\n第11集 <play>web_m3u8<\/play>https%3a%2f%2f2%2emhbobo%2ecom%2f20190905%2fTtVMAtbC%2findex%2em3u8\r\n第12集 <play>web_m3u8<\/play>https%3a%2f%2f2%2emhbobo%2ecom%2f20190905%2flXfdswZ3%2findex%2em3u8\r\n第13集 <play>web_m3u8<\/play>https%3a%2f%2f2%2emhbobo%2ecom%2f20190905%2fRBpQtI5b%2findex%2em3u8\r\n第14集 <play>web_m3u8<\/play>https%3a%2f%2f2%2emhbobo%2ecom%2f20190905%2fxj3Ghu1C%2findex%2em3u8\r\n第15集 <play>web_m3u8<\/play>https%3a%2f%2f2%2emhbobo%2ecom%2f20190905%2fAc0oBe55%2findex%2em3u8\r\n第16集 <play>web_m3u8<\/play>https%3a%2f%2f2%2emhbobo%2ecom%2f20190905%2fSVnjIYPD%2findex%2em3u8\r\n第17集 <play>web_m3u8<\/play>https%3a%2f%2f2%2emhbobo%2ecom%2f20190905%2f6lUWgms4%2findex%2em3u8\r\n第18集 <play>web_m3u8<\/play>https%3a%2f%2f2%2emhbobo%2ecom%2f20190905%2fwvNPGt35%2findex%2em3u8\r\n第19集 <play>web_m3u8<\/play>https%3a%2f%2f2%2emhbobo%2ecom%2f20190905%2fuSvbG3CD%2findex%2em3u8\r\n第20集 <play>web_m3u8<\/play>https%3a%2f%2f2%2emhbobo%2ecom%2f20190905%2fi2TE3yjp%2findex%2em3u8\r\n第21集 <play>web_m3u8<\/play>https%3a%2f%2f2%2emhbobo%2ecom%2f20190905%2f7lRrnUTo%2findex%2em3u8\r\n第22集 <play>web_m3u8<\/play>https%3a%2f%2f2%2emhbobo%2ecom%2f20190905%2fA8RyZJC9%2findex%2em3u8\r\n第23集 <play>web_m3u8<\/play>https%3a%2f%2f2%2emhbobo%2ecom%2f20190905%2fwUTUD4MO%2findex%2em3u8\r\n第24集 <play>web_m3u8<\/play>https%3a%2f%2f2%2emhbobo%2ecom%2f20190905%2fG4ryJOuh%2findex%2em3u8\r\n第25集 <play>web_m3u8<\/play>https%3a%2f%2f2%2emhbobo%2ecom%2f20190905%2fFLUZV9E4%2findex%2em3u8\r\n第26集 <play>web_m3u8<\/play>https%3a%2f%2f2%2emhbobo%2ecom%2f20190905%2fAq18ct0Y%2findex%2em3u8\r\n第27集 <play>web_m3u8<\/play>https%3a%2f%2f2%2emhbobo%2ecom%2f20190905%2fZp6n08sE%2findex%2em3u8\r\n第28集 <play>web_m3u8<\/play>https%3a%2f%2f2%2emhbobo%2ecom%2f20190905%2f5j8QA4pH%2findex%2em3u8\r\n第29集 <play>web_m3u8<\/play>https%3a%2f%2f2%2emhbobo%2ecom%2f20190905%2fRCySsDlW%2findex%2em3u8\r\n第30集 <play>web_m3u8<\/play>https%3a%2f%2f2%2emhbobo%2ecom%2f20190905%2frtwiQWYP%2findex%2em3u8\r\n第31集 <play>web_m3u8<\/play>https%3a%2f%2f2%2emhbobo%2ecom%2f20190905%2finUDu0Cd%2findex%2em3u8\r\n第32集 <play>web_m3u8<\/play>https%3a%2f%2f2%2emhbobo%2ecom%2f20190905%2fpuDfyrMq%2findex%2em3u8\r\n第33集 <play>web_m3u8<\/play>https%3a%2f%2f2%2emhbobo%2ecom%2f20190905%2fcEe9hG22%2findex%2em3u8\r\n第34集 <play>web_m3u8<\/play>https%3a%2f%2f2%2emhbobo%2ecom%2f20190905%2fHLbnDTSk%2findex%2em3u8\r\n第35集 <play>web_m3u8<\/play>https%3a%2f%2f2%2emhbobo%2ecom%2f20190905%2fhR13kS57%2findex%2em3u8\r\n第36集 <play>web_m3u8<\/play>https%3a%2f%2f2%2emhbobo%2ecom%2f20190905%2f97KEVqmy%2findex%2em3u8\r\n第37集 <play>web_m3u8<\/play>https%3a%2f%2f2%2emhbobo%2ecom%2f20190905%2fjZF79KDA%2findex%2em3u8\r\n第38集 <play>web_m3u8<\/play>https%3a%2f%2f2%2emhbobo%2ecom%2f20190905%2fwd3tGZ9p%2findex%2em3u8\r\n第39集 <play>web_m3u8<\/play>https%3a%2f%2f2%2emhbobo%2ecom%2f20190905%2fWPiuiehZ%2findex%2em3u8\r\n第40集 <play>web_m3u8<\/play>https%3a%2f%2f2%2emhbobo%2ecom%2f20190905%2fqUn1Zmc4%2findex%2em3u8","R在线播放2":"第41集 阴谋 <play>爱奇艺接口<\/play>//www.iqiyi.com/v_19rrerllqw.html\r\n第42集 闷棍 <play>爱奇艺接口<\/play>//www.iqiyi.com/v_19rrez3n8g.html\r\n第43集 白银级 <play>爱奇艺接口<\/play>//www.iqiyi.com/v_19rrez3qyg.html\r\n第44集 遇害 <play>爱奇艺接口<\/play>//www.iqiyi.com/v_19rrez4vrw.html\r\n第45集 被骗了 <play>爱奇艺接口<\/play>//www.iqiyi.com/v_19rrfmdmww.html\r\n第46集 怀疑的种子 <play>爱奇艺接口<\/play>//www.iqiyi.com/v_19rrfsn0b4.html\r\n第47集 告发 <play>爱奇艺接口<\/play>//www.iqiyi.com/v_19rrfsn068.html\r\n第48集 炼丹 <play>爱奇艺接口<\/play>//www.iqiyi.com/v_19rrfsn2sk.html\r\n第49集 第49集 危机 <play>爱奇艺接口<\/play>//www.iqiyi.com/v_19rrfe3wfw.html\r\n第50集 陷阱 <play>爱奇艺接口<\/play>//www.iqiyi.com/v_19rrfakrq4.html\r\n第51集 过去 <play>爱奇艺接口<\/play>//www.iqiyi.com/v_19rrfalu9k.html\r\n第52集 第52集 风雪草 <play>爱奇艺接口<\/play>//www.iqiyi.com/v_19rrfg3q10.html\r\n第53集 第53集 风雪灵冢 <play>爱奇艺接口<\/play>//www.iqiyi.com/v_19rrfg3snc.html\r\n第54集 第54集 被困 <play>爱奇艺接口<\/play>//www.iqiyi.com/v_19rrfg3sao.html\r\n第55集 第55集 刻印 <play>爱奇艺接口<\/play>//www.iqiyi.com/v_19rrfg3s7k.html\r\n第56集 脱困 <play>爱奇艺接口<\/play>//www.iqiyi.com/v_19rrbouobc.html\r\n第57集 指控 <play>爱奇艺接口<\/play>//www.iqiyi.com/v_19rrbxbmh8.html\r\n第58集 丹药 <play>爱奇艺接口<\/play>//www.iqiyi.com/v_19rrbu9hn8.html\r\n第59集 任务 <play>爱奇艺接口<\/play>//www.iqiyi.com/v_19rrbhr5es.html\r\n第60集 父女 <play>爱奇艺接口<\/play>//www.iqiyi.com/v_19rrbfa4us.html\r\n第61集 管理员 <play>爱奇艺接口<\/play>//www.iqiyi.com/v_19rrbdzd7g.html\r\n第62集 双修 <play>爱奇艺接口<\/play>//www.iqiyi.com/v_19rrbl4lqk.html\r\n第63集 成丹 <play>爱奇艺接口<\/play>//www.iqiyi.com/v_19rrbihqpc.html\r\n第64集 偷袭 <play>爱奇艺接口<\/play>//www.iqiyi.com/v_19rrcad1pc.html\r\n第65集 美人恩重 <play>爱奇艺接口<\/play>//www.iqiyi.com/v_19rrc7t8u4.html\r\n第66集 偷窃 <play>爱奇艺接口<\/play>//www.iqiyi.com/v_19rrcepjd0.html\r\n第67集 测试 <play>爱奇艺接口<\/play>//www.iqiyi.com/v_19rrc24lu4.html\r\n第68集 朋友 <play>爱奇艺接口<\/play>//www.iqiyi.com/v_19rrby1kg8.html\r\n第69集 秘境 <play>爱奇艺接口<\/play>//www.iqiyi.com/v_19rrc5xofw.html\r\n第70集 冰封的思念 <play>爱奇艺接口<\/play>//www.iqiyi.com/v_19rrc2wjuw.html\r\n第71集 幻象 <play>爱奇艺接口<\/play>//www.iqiyi.com/v_19rrcto6g0.html\r\n第72集 周旋 <play>爱奇艺接口<\/play>//www.iqiyi.com/v_19rrczn9kc.html\r\n第73集 激斗 <play>爱奇艺接口<\/play>//www.iqiyi.com/v_19rrcwt9c8.html\r\n第74集 交易 <play>爱奇艺接口<\/play>//www.iqiyi.com/v_19rrcwt634.html\r\n第75集 计谋 <play>爱奇艺接口<\/play>//www.iqiyi.com/v_19rrcpgbik.html\r\n第76集 金蝉脱壳 <play>爱奇艺接口<\/play>//www.iqiyi.com/v_19rrcmv5yw.html\r\n第77集 风雪神将 <play>爱奇艺接口<\/play>//www.iqiyi.com/v_19rrdcqqaw.html\r\n第78集 幻象 <play>爱奇艺接口<\/play>//www.iqiyi.com/v_19rrdj5n0c.html\r\n第79集 噬魂幻境 <play>爱奇艺接口<\/play>//www.iqiyi.com/v_19rrd6683c.html\r\n第80集 赢了 <play>爱奇艺接口<\/play>//www.iqiyi.com/v_19rrd1fcic.html","R封面图":"https://sc04.alicdn.com/kf/H26a57e15a39d4330aa6e17007e10755fs.jpg","R在线播放4":"","AID":"20180349","R系列":"妖神记","R播放状态":"完结","R备用":"","R原版名称":"妖神记 第二季","R原作":"发飙的蜗牛","R简介_br":"神秘瑰丽的妖灵世界，奇奥无穷的时空妖灵之书，聂离追寻着世界的真相。美丽温柔的叶紫芸、倔强高傲的肖凝儿，面对两位女神的青睐，他该如何抉择？还有患难与共的兄弟，一起修炼最强功法、最强妖灵之力，踏足武道巅峰。","R在线播放All":[[],[{"PlayVid":"//www.iqiyi.com/v_19rrerllqw.html","Ex":"","Title_l":"第41集 阴谋","Title":"第41集","EpName":"41","PlayId":"<play>爱奇艺接口<\/play>","EpPic":""},{"PlayVid":"//www.iqiyi.com/v_19rrez3n8g.html","Ex":"","Title_l":"第42集 闷棍","Title":"第42集","EpName":"42","PlayId":"<play>爱奇艺接口<\/play>","EpPic":""},{"PlayVid":"//www.iqiyi.com/v_19rrez3qyg.html","Ex":"","Title_l":"第43集 白银级","Title":"第43集","EpName":"43","PlayId":"<play>爱奇艺接口<\/play>","EpPic":""},{"PlayVid":"//www.iqiyi.com/v_19rrez4vrw.html","Ex":"","Title_l":"第44集 遇害","Title":"第44集","EpName":"44","PlayId":"<play>爱奇艺接口<\/play>","EpPic":""},{"PlayVid":"//www.iqiyi.com/v_19rrfmdmww.html","Ex":"","Title_l":"第45集 被骗了","Title":"第45集","EpName":"45","PlayId":"<play>爱奇艺接口<\/play>","EpPic":""},{"PlayVid":"//www.iqiyi.com/v_19rrfsn0b4.html","Ex":"","Title_l":"第46集 怀疑的种子","Title":"第46集","EpName":"46","PlayId":"<play>爱奇艺接口<\/play>","EpPic":""},{"PlayVid":"//www.iqiyi.com/v_19rrfsn068.html","Ex":"","Title_l":"第47集 告发","Title":"第47集","EpName":"47","PlayId":"<play>爱奇艺接口<\/play>","EpPic":""},{"PlayVid":"//www.iqiyi.com/v_19rrfsn2sk.html","Ex":"","Title_l":"第48集 炼丹","Title":"第48集","EpName":"48","PlayId":"<play>爱奇艺接口<\/play>","EpPic":""},{"PlayVid":"//www.iqiyi.com/v_19rrfe3wfw.html","Ex":"","Title_l":"第49集 第49集 危机","Title":"第49集","EpName":"49","PlayId":"<play>爱奇艺接口<\/play>","EpPic":""},{"PlayVid":"//www.iqiyi.com/v_19rrfakrq4.html","Ex":"","Title_l":"第50集 陷阱","Title":"第50集","EpName":"50","PlayId":"<play>爱奇艺接口<\/play>","EpPic":""},{"PlayVid":"//www.iqiyi.com/v_19rrfalu9k.html","Ex":"","Title_l":"第51集 过去","Title":"第51集","EpName":"51","PlayId":"<play>爱奇艺接口<\/play>","EpPic":""},{"PlayVid":"//www.iqiyi.com/v_19rrfg3q10.html","Ex":"","Title_l":"第52集 第52集 风雪草","Title":"第52集","EpName":"52","PlayId":"<play>爱奇艺接口<\/play>","EpPic":""},{"PlayVid":"//www.iqiyi.com/v_19rrfg3snc.html","Ex":"","Title_l":"第53集 第53集 风雪灵冢","Title":"第53集","EpName":"53","PlayId":"<play>爱奇艺接口<\/play>","EpPic":""},{"PlayVid":"//www.iqiyi.com/v_19rrfg3sao.html","Ex":"","Title_l":"第54集 第54集 被困","Title":"第54集","EpName":"54","PlayId":"<play>爱奇艺接口<\/play>","EpPic":""},{"PlayVid":"//www.iqiyi.com/v_19rrfg3s7k.html","Ex":"","Title_l":"第55集 第55集 刻印","Title":"第55集","EpName":"55","PlayId":"<play>爱奇艺接口<\/play>","EpPic":""},{"PlayVid":"//www.iqiyi.com/v_19rrbouobc.html","Ex":"","Title_l":"第56集 脱困","Title":"第56集","EpName":"56","PlayId":"<play>爱奇艺接口<\/play>","EpPic":""},{"PlayVid":"//www.iqiyi.com/v_19rrbxbmh8.html","Ex":"","Title_l":"第57集 指控","Title":"第57集","EpName":"57","PlayId":"<play>爱奇艺接口<\/play>","EpPic":""},{"PlayVid":"//www.iqiyi.com/v_19rrbu9hn8.html","Ex":"","Title_l":"第58集 丹药","Title":"第58集","EpName":"58","PlayId":"<play>爱奇艺接口<\/play>","EpPic":""},{"PlayVid":"//www.iqiyi.com/v_19rrbhr5es.html","Ex":"","Title_l":"第59集 任务","Title":"第59集","EpName":"59","PlayId":"<play>爱奇艺接口<\/play>","EpPic":""},{"PlayVid":"//www.iqiyi.com/v_19rrbfa4us.html","Ex":"","Title_l":"第60集 父女","Title":"第60集","EpName":"60","PlayId":"<play>爱奇艺接口<\/play>","EpPic":""},{"PlayVid":"//www.iqiyi.com/v_19rrbdzd7g.html","Ex":"","Title_l":"第61集 管理员","Title":"第61集","EpName":"61","PlayId":"<play>爱奇艺接口<\/play>","EpPic":""},{"PlayVid":"//www.iqiyi.com/v_19rrbl4lqk.html","Ex":"","Title_l":"第62集 双修","Title":"第62集","EpName":"62","PlayId":"<play>爱奇艺接口<\/play>","EpPic":""},{"PlayVid":"//www.iqiyi.com/v_19rrbihqpc.html","Ex":"","Title_l":"第63集 成丹","Title":"第63集","EpName":"63","PlayId":"<play>爱奇艺接口<\/play>","EpPic":""},{"PlayVid":"//www.iqiyi.com/v_19rrcad1pc.html","Ex":"","Title_l":"第64集 偷袭","Title":"第64集","EpName":"64","PlayId":"<play>爱奇艺接口<\/play>","EpPic":""},{"PlayVid":"//www.iqiyi.com/v_19rrc7t8u4.html","Ex":"","Title_l":"第65集 美人恩重","Title":"第65集","EpName":"65","PlayId":"<play>爱奇艺接口<\/play>","EpPic":""},{"PlayVid":"//www.iqiyi.com/v_19rrcepjd0.html","Ex":"","Title_l":"第66集 偷窃","Title":"第66集","EpName":"66","PlayId":"<play>爱奇艺接口<\/play>","EpPic":""},{"PlayVid":"//www.iqiyi.com/v_19rrc24lu4.html","Ex":"","Title_l":"第67集 测试","Title":"第67集","EpName":"67","PlayId":"<play>爱奇艺接口<\/play>","EpPic":""},{"PlayVid":"//www.iqiyi.com/v_19rrby1kg8.html","Ex":"","Title_l":"第68集 朋友","Title":"第68集","EpName":"68","PlayId":"<play>爱奇艺接口<\/play>","EpPic":""},{"PlayVid":"//www.iqiyi.com/v_19rrc5xofw.html","Ex":"","Title_l":"第69集 秘境","Title":"第69集","EpName":"69","PlayId":"<play>爱奇艺接口<\/play>","EpPic":""},{"PlayVid":"//www.iqiyi.com/v_19rrc2wjuw.html","Ex":"","Title_l":"第70集 冰封的思念","Title":"第70集","EpName":"70","PlayId":"<play>爱奇艺接口<\/play>","EpPic":""},{"PlayVid":"//www.iqiyi.com/v_19rrcto6g0.html","Ex":"","Title_l":"第71集 幻象","Title":"第71集","EpName":"71","PlayId":"<play>爱奇艺接口<\/play>","EpPic":""},{"PlayVid":"//www.iqiyi.com/v_19rrczn9kc.html","Ex":"","Title_l":"第72集 周旋","Title":"第72集","EpName":"72","PlayId":"<play>爱奇艺接口<\/play>","EpPic":""},{"PlayVid":"//www.iqiyi.com/v_19rrcwt9c8.html","Ex":"","Title_l":"第73集 激斗","Title":"第73集","EpName":"73","PlayId":"<play>爱奇艺接口<\/play>","EpPic":""},{"PlayVid":"//www.iqiyi.com/v_19rrcwt634.html","Ex":"","Title_l":"第74集 交易","Title":"第74集","EpName":"74","PlayId":"<play>爱奇艺接口<\/play>","EpPic":""},{"PlayVid":"//www.iqiyi.com/v_19rrcpgbik.html","Ex":"","Title_l":"第75集 计谋","Title":"第75集","EpName":"75","PlayId":"<play>爱奇艺接口<\/play>","EpPic":""},{"PlayVid":"//www.iqiyi.com/v_19rrcmv5yw.html","Ex":"","Title_l":"第76集 金蝉脱壳","Title":"第76集","EpName":"76","PlayId":"<play>爱奇艺接口<\/play>","EpPic":""},{"PlayVid":"//www.iqiyi.com/v_19rrdcqqaw.html","Ex":"","Title_l":"第77集 风雪神将","Title":"第77集","EpName":"77","PlayId":"<play>爱奇艺接口<\/play>","EpPic":""},{"PlayVid":"//www.iqiyi.com/v_19rrdj5n0c.html","Ex":"","Title_l":"第78集 幻象","Title":"第78集","EpName":"78","PlayId":"<play>爱奇艺接口<\/play>","EpPic":""},{"PlayVid":"//www.iqiyi.com/v_19rrd6683c.html","Ex":"","Title_l":"第79集 噬魂幻境","Title":"第79集","EpName":"79","PlayId":"<play>爱奇艺接口<\/play>","EpPic":""},{"PlayVid":"//www.iqiyi.com/v_19rrd1fcic.html","Ex":"","Title_l":"第80集 赢了","Title":"第80集","EpName":"80","PlayId":"<play>爱奇艺接口<\/play>","EpPic":""}],[{"PlayVid":"https%3a%2f%2f2%2emhbobo%2ecom%2f20190905%2fFuhHYM8F%2findex%2em3u8","Ex":"","Title_l":"第1集","Title":"第1集","EpName":"1","PlayId":"<play>web_m3u8<\/play>","EpPic":""},{"PlayVid":"https%3a%2f%2f2%2emhbobo%2ecom%2f20190905%2fwxPwauSL%2findex%2em3u8","Ex":"","Title_l":"第2集","Title":"第2集","EpName":"2","PlayId":"<play>web_m3u8<\/play>","EpPic":""},{"PlayVid":"https%3a%2f%2f2%2emhbobo%2ecom%2f20190905%2fYbUpQjqV%2findex%2em3u8","Ex":"","Title_l":"第3集","Title":"第3集","EpName":"3","PlayId":"<play>web_m3u8<\/play>","EpPic":""},{"PlayVid":"https%3a%2f%2f2%2emhbobo%2ecom%2f20190905%2f5bxHxGhQ%2findex%2em3u8","Ex":"","Title_l":"第4集","Title":"第4集","EpName":"4","PlayId":"<play>web_m3u8<\/play>","EpPic":""},{"PlayVid":"https%3a%2f%2f2%2emhbobo%2ecom%2f20190905%2f4fQgUbCc%2findex%2em3u8","Ex":"","Title_l":"第5集","Title":"第5集","EpName":"5","PlayId":"<play>web_m3u8<\/play>","EpPic":""},{"PlayVid":"https%3a%2f%2f2%2emhbobo%2ecom%2f20190905%2fHrN2o89e%2findex%2em3u8","Ex":"","Title_l":"第6集","Title":"第6集","EpName":"6","PlayId":"<play>web_m3u8<\/play>","EpPic":""},{"PlayVid":"https%3a%2f%2f2%2emhbobo%2ecom%2f20190905%2f7SjZr6G3%2findex%2em3u8","Ex":"","Title_l":"第7集","Title":"第7集","EpName":"7","PlayId":"<play>web_m3u8<\/play>","EpPic":""},{"PlayVid":"https%3a%2f%2f2%2emhbobo%2ecom%2f20190905%2f6xLQZ9yB%2findex%2em3u8","Ex":"","Title_l":"第8集","Title":"第8集","EpName":"8","PlayId":"<play>web_m3u8<\/play>","EpPic":""},{"PlayVid":"https%3a%2f%2f2%2emhbobo%2ecom%2f20190905%2fv14bZ3KF%2findex%2em3u8","Ex":"","Title_l":"第9集","Title":"第9集","EpName":"9","PlayId":"<play>web_m3u8<\/play>","EpPic":""},{"PlayVid":"https%3a%2f%2f2%2emhbobo%2ecom%2f20190905%2fzuhSjjvK%2findex%2em3u8","Ex":"","Title_l":"第10集","Title":"第10集","EpName":"10","PlayId":"<play>web_m3u8<\/play>","EpPic":""},{"PlayVid":"https%3a%2f%2f2%2emhbobo%2ecom%2f20190905%2fTtVMAtbC%2findex%2em3u8","Ex":"","Title_l":"第11集","Title":"第11集","EpName":"11","PlayId":"<play>web_m3u8<\/play>","EpPic":""},{"PlayVid":"https%3a%2f%2f2%2emhbobo%2ecom%2f20190905%2flXfdswZ3%2findex%2em3u8","Ex":"","Title_l":"第12集","Title":"第12集","EpName":"12","PlayId":"<play>web_m3u8<\/play>","EpPic":""},{"PlayVid":"https%3a%2f%2f2%2emhbobo%2ecom%2f20190905%2fRBpQtI5b%2findex%2em3u8","Ex":"","Title_l":"第13集","Title":"第13集","EpName":"13","PlayId":"<play>web_m3u8<\/play>","EpPic":""},{"PlayVid":"https%3a%2f%2f2%2emhbobo%2ecom%2f20190905%2fxj3Ghu1C%2findex%2em3u8","Ex":"","Title_l":"第14集","Title":"第14集","EpName":"14","PlayId":"<play>web_m3u8<\/play>","EpPic":""},{"PlayVid":"https%3a%2f%2f2%2emhbobo%2ecom%2f20190905%2fAc0oBe55%2findex%2em3u8","Ex":"","Title_l":"第15集","Title":"第15集","EpName":"15","PlayId":"<play>web_m3u8<\/play>","EpPic":""},{"PlayVid":"https%3a%2f%2f2%2emhbobo%2ecom%2f20190905%2fSVnjIYPD%2findex%2em3u8","Ex":"","Title_l":"第16集","Title":"第16集","EpName":"16","PlayId":"<play>web_m3u8<\/play>","EpPic":""},{"PlayVid":"https%3a%2f%2f2%2emhbobo%2ecom%2f20190905%2f6lUWgms4%2findex%2em3u8","Ex":"","Title_l":"第17集","Title":"第17集","EpName":"17","PlayId":"<play>web_m3u8<\/play>","EpPic":""},{"PlayVid":"https%3a%2f%2f2%2emhbobo%2ecom%2f20190905%2fwvNPGt35%2findex%2em3u8","Ex":"","Title_l":"第18集","Title":"第18集","EpName":"18","PlayId":"<play>web_m3u8<\/play>","EpPic":""},{"PlayVid":"https%3a%2f%2f2%2emhbobo%2ecom%2f20190905%2fuSvbG3CD%2findex%2em3u8","Ex":"","Title_l":"第19集","Title":"第19集","EpName":"19","PlayId":"<play>web_m3u8<\/play>","EpPic":""},{"PlayVid":"https%3a%2f%2f2%2emhbobo%2ecom%2f20190905%2fi2TE3yjp%2findex%2em3u8","Ex":"","Title_l":"第20集","Title":"第20集","EpName":"20","PlayId":"<play>web_m3u8<\/play>","EpPic":""},{"PlayVid":"https%3a%2f%2f2%2emhbobo%2ecom%2f20190905%2f7lRrnUTo%2findex%2em3u8","Ex":"","Title_l":"第21集","Title":"第21集","EpName":"21","PlayId":"<play>web_m3u8<\/play>","EpPic":""},{"PlayVid":"https%3a%2f%2f2%2emhbobo%2ecom%2f20190905%2fA8RyZJC9%2findex%2em3u8","Ex":"","Title_l":"第22集","Title":"第22集","EpName":"22","PlayId":"<play>web_m3u8<\/play>","EpPic":""},{"PlayVid":"https%3a%2f%2f2%2emhbobo%2ecom%2f20190905%2fwUTUD4MO%2findex%2em3u8","Ex":"","Title_l":"第23集","Title":"第23集","EpName":"23","PlayId":"<play>web_m3u8<\/play>","EpPic":""},{"PlayVid":"https%3a%2f%2f2%2emhbobo%2ecom%2f20190905%2fG4ryJOuh%2findex%2em3u8","Ex":"","Title_l":"第24集","Title":"第24集","EpName":"24","PlayId":"<play>web_m3u8<\/play>","EpPic":""},{"PlayVid":"https%3a%2f%2f2%2emhbobo%2ecom%2f20190905%2fFLUZV9E4%2findex%2em3u8","Ex":"","Title_l":"第25集","Title":"第25集","EpName":"25","PlayId":"<play>web_m3u8<\/play>","EpPic":""},{"PlayVid":"https%3a%2f%2f2%2emhbobo%2ecom%2f20190905%2fAq18ct0Y%2findex%2em3u8","Ex":"","Title_l":"第26集","Title":"第26集","EpName":"26","PlayId":"<play>web_m3u8<\/play>","EpPic":""},{"PlayVid":"https%3a%2f%2f2%2emhbobo%2ecom%2f20190905%2fZp6n08sE%2findex%2em3u8","Ex":"","Title_l":"第27集","Title":"第27集","EpName":"27","PlayId":"<play>web_m3u8<\/play>","EpPic":""},{"PlayVid":"https%3a%2f%2f2%2emhbobo%2ecom%2f20190905%2f5j8QA4pH%2findex%2em3u8","Ex":"","Title_l":"第28集","Title":"第28集","EpName":"28","PlayId":"<play>web_m3u8<\/play>","EpPic":""},{"PlayVid":"https%3a%2f%2f2%2emhbobo%2ecom%2f20190905%2fRCySsDlW%2findex%2em3u8","Ex":"","Title_l":"第29集","Title":"第29集","EpName":"29","PlayId":"<play>web_m3u8<\/play>","EpPic":""},{"PlayVid":"https%3a%2f%2f2%2emhbobo%2ecom%2f20190905%2frtwiQWYP%2findex%2em3u8","Ex":"","Title_l":"第30集","Title":"第30集","EpName":"30","PlayId":"<play>web_m3u8<\/play>","EpPic":""},{"PlayVid":"https%3a%2f%2f2%2emhbobo%2ecom%2f20190905%2finUDu0Cd%2findex%2em3u8","Ex":"","Title_l":"第31集","Title":"第31集","EpName":"31","PlayId":"<play>web_m3u8<\/play>","EpPic":""},{"PlayVid":"https%3a%2f%2f2%2emhbobo%2ecom%2f20190905%2fpuDfyrMq%2findex%2em3u8","Ex":"","Title_l":"第32集","Title":"第32集","EpName":"32","PlayId":"<play>web_m3u8<\/play>","EpPic":""},{"PlayVid":"https%3a%2f%2f2%2emhbobo%2ecom%2f20190905%2fcEe9hG22%2findex%2em3u8","Ex":"","Title_l":"第33集","Title":"第33集","EpName":"33","PlayId":"<play>web_m3u8<\/play>","EpPic":""},{"PlayVid":"https%3a%2f%2f2%2emhbobo%2ecom%2f20190905%2fHLbnDTSk%2findex%2em3u8","Ex":"","Title_l":"第34集","Title":"第34集","EpName":"34","PlayId":"<play>web_m3u8<\/play>","EpPic":""},{"PlayVid":"https%3a%2f%2f2%2emhbobo%2ecom%2f20190905%2fhR13kS57%2findex%2em3u8","Ex":"","Title_l":"第35集","Title":"第35集","EpName":"35","PlayId":"<play>web_m3u8<\/play>","EpPic":""},{"PlayVid":"https%3a%2f%2f2%2emhbobo%2ecom%2f20190905%2f97KEVqmy%2findex%2em3u8","Ex":"","Title_l":"第36集","Title":"第36集","EpName":"36","PlayId":"<play>web_m3u8<\/play>","EpPic":""},{"PlayVid":"https%3a%2f%2f2%2emhbobo%2ecom%2f20190905%2fjZF79KDA%2findex%2em3u8","Ex":"","Title_l":"第37集","Title":"第37集","EpName":"37","PlayId":"<play>web_m3u8<\/play>","EpPic":""},{"PlayVid":"https%3a%2f%2f2%2emhbobo%2ecom%2f20190905%2fwd3tGZ9p%2findex%2em3u8","Ex":"","Title_l":"第38集","Title":"第38集","EpName":"38","PlayId":"<play>web_m3u8<\/play>","EpPic":""},{"PlayVid":"https%3a%2f%2f2%2emhbobo%2ecom%2f20190905%2fWPiuiehZ%2findex%2em3u8","Ex":"","Title_l":"第39集","Title":"第39集","EpName":"39","PlayId":"<play>web_m3u8<\/play>","EpPic":""},{"PlayVid":"https%3a%2f%2f2%2emhbobo%2ecom%2f20190905%2fqUn1Zmc4%2findex%2em3u8","Ex":"","Title_l":"第40集","Title":"第40集","EpName":"40","PlayId":"<play>web_m3u8<\/play>","EpPic":""}],[]],"R资源类型":"","R标签":"热血 冒险 战斗","R推荐星级":2,"R首播年份":"2018","R动画种类":"WEB","R官方网站":"暂无","R动画名称":"妖神记 第二季","R更新时间unix":1554702628,"R剧情类型":"热血 冒险 战斗","R字母索引":"Y","R网盘资源":"(暂缺)","R视频尺寸":"720P/1080P","RankCnt":24005,"CollectCnt":41,"R首播时间":"2018-01-06","R网盘资源2":[],"R封面图小":"https://sc04.alicdn.com/kf/H599d254af50745e6ab6c486697fce32at.jpg","R新番标题":"第80集(完结)"}}