{"AniPreSim":[{"Title":"我是大仙尊","Href":"/detail/20200231","NewTitle":"第73集","AID":"20200231","PicSmall":"https://sc04.alicdn.com/kf/H7593e341979b4310b40f5ecc096e9ae4N.jpg"},{"Title":"彗星路西法","Href":"/detail/20150031","NewTitle":"[TV 01-12]","AID":"20150031","PicSmall":"https://sc04.alicdn.com/kf/H5252f356e6e34f7bb2b28aa189eae857d.jpg"},{"Title":"因为太怕痛就全点防御力了","Href":"/detail/20200008","NewTitle":"[BD 01-12]","AID":"20200008","PicSmall":"https://sc04.alicdn.com/kf/Hf242cb2e11cf47f4a67c7c1279ace40co.jpg"},{"Title":"潘多拉与小哈欠","Href":"/detail/20190428","NewTitle":"第2话(完结)","AID":"20190428","PicSmall":"https://sc04.alicdn.com/kf/Hd62fe911749443588b8087be604e0f92u.jpg"},{"Title":"贤者之孙","Href":"/detail/20190060","NewTitle":"[TV 01-12]","AID":"20190060","PicSmall":"https://sc04.alicdn.com/kf/H029fb2058fc7422593a70a2e0a2bcbe40.jpg"},{"Title":"月光下的异世界之旅","Href":"/detail/20210025","NewTitle":"PV","AID":"20210025","PicSmall":"https://sc04.alicdn.com/kf/Hb2ef19b5f6844cee89e7516b22354f7fX.jpg"},{"Title":"自称贤者弟子的贤者","Href":"/detail/20210155","NewTitle":"PV","AID":"20210155","PicSmall":"https://pic.rmb.bdstatic.com/bjh/a1ec34e96567b24bc785ec7358ccb628.jpeg"},{"Title":"国王排名","Href":"/detail/20210169","NewTitle":"PV","AID":"20210169","PicSmall":"https://pic.rmb.bdstatic.com/bjh/7a4a466dac07c55334ab8f641e847bba.jpeg"}],"Tip":"AGE动漫网 备用地址：<a rel=\"nofollow\" target=\"_blank\" href=\"http://www.agefans.cc\" style=\"color: #60b8cc;text-decoration:  none;\">www.agefans.cc<\/a> 欢迎大家分享给身边朋友！为确保正常观看，请使用谷歌浏览器。","AniPreRel":[{"Title":"仙剑奇侠传幻璃镜","Href":"/detail/20190320","NewTitle":"第2集(完结)","AID":"20190320","PicSmall":"https://sc04.alicdn.com/kf/Haf4f5c9ef89c4854ac6d39655440ffa3c.jpg"}],"AniInfo":{"CommentCnt":11,"R更新时间str2":"2019-10-02","R剧情类型2":["冒险","奇幻","玄幻"],"R简介":"网络动画《仙剑奇侠传幻璃镜》改编自同名手机游戏，是《仙剑奇侠传》系列衍生作品中的首部动画作品。动画于2019年10月2日起每周三在爱奇艺独家发布。该作基于同名手游世界观进行创作，并首次以\u201c妖\u201d为主角，讲述了猫妖檀霜、画妖黛砚、树妖青槐为了逃脱\u201c幻境\u201d的冒险故事。","R其它名称":"幻璃镜","R地区":"中国","R在线播放":"","LastModified":"Mon, 10 Mar 2031 23:05:14 GMT","R更新时间str":"2019-10-02 23:43:24","R制作公司":"暂无","R标签2":["冒险","奇幻","玄幻"],"ModifiedTime":1615561514,"R标题V2":"","R首播季度":"10","R更新时间":"20191002234324","DEF_PLAYINDEX":"1","R在线播放3":"第01话 <play>web_m3u8<\/play>https://gnzk.yiya520.com/2019/10/02/4sZwWTdPyd6AQKP1/playlist.m3u8\r\n第02话 <play>web_m3u8<\/play>https://gnzk.yiya520.com/2019/10/02/APN7Y35H4FUOxp56/playlist.m3u8","R在线播放2":"第01集 <play>web_m3u8<\/play>https://qq.com-ok-qq.com/20191002/24033_ca0c3ce6/index.m3u8\r\n第02集 <play>web_m3u8<\/play>https://qq.com-ok-qq.com/20191002/24034_35f54f78/index.m3u8","R封面图":"https://sc04.alicdn.com/kf/Hdfb7caec058c4241a31bc712d610dc489.jpg","R在线播放4":"","AID":"20190320","R系列":"仙剑奇侠传","R播放状态":"完结","R备用":"","R原版名称":"仙剑奇侠传幻璃镜","R原作":"暂无","R简介_br":"网络动画《仙剑奇侠传幻璃镜》改编自同名手机游戏，是《仙剑奇侠传》系列衍生作品中的首部动画作品。动画于2019年10月2日起每周三在爱奇艺独家发布。该作基于同名手游世界观进行创作，并首次以\u201c妖\u201d为主角，讲述了猫妖檀霜、画妖黛砚、树妖青槐为了逃脱\u201c幻境\u201d的冒险故事。","R在线播放All":[[],[{"PlayVid":"https://qq.com-ok-qq.com/20191002/24033_ca0c3ce6/index.m3u8","Ex":"","Title_l":"第01集","Title":"第01集","EpName":"1","PlayId":"<play>web_m3u8<\/play>","EpPic":""},{"PlayVid":"https://qq.com-ok-qq.com/20191002/24034_35f54f78/index.m3u8","Ex":"","Title_l":"第02集","Title":"第02集","EpName":"2","PlayId":"<play>web_m3u8<\/play>","EpPic":""}],[{"PlayVid":"https://gnzk.yiya520.com/2019/10/02/4sZwWTdPyd6AQKP1/playlist.m3u8","Ex":"","Title_l":"第01话","Title":"第01话","EpName":"1","PlayId":"<play>web_m3u8<\/play>","EpPic":""},{"PlayVid":"https://gnzk.yiya520.com/2019/10/02/APN7Y35H4FUOxp56/playlist.m3u8","Ex":"","Title_l":"第02话","Title":"第02话","EpName":"2","PlayId":"<play>web_m3u8<\/play>","EpPic":""}],[]],"R资源类型":"","R标签":"冒险 奇幻 玄幻","R推荐星级":2,"R首播年份":"2019","R动画种类":"WEB","R官方网站":"暂无","R动画名称":"仙剑奇侠传幻璃镜","R更新时间unix":1570031004,"R剧情类型":"冒险 奇幻 玄幻","R字母索引":"X","R网盘资源":"(暂缺)","R视频尺寸":"720P/1080P","RankCnt":2189,"CollectCnt":27,"R首播时间":"2019-10-02","R网盘资源2":[],"R封面图小":"https://sc04.alicdn.com/kf/Haf4f5c9ef89c4854ac6d39655440ffa3c.jpg","R新番标题":"第2集(完结)"}}