{"AniPreSim":[{"Title":"动态漫画·元尊","Href":"/detail/20200155","NewTitle":"第13集(完结)","AID":"20200155","PicSmall":"https://sc04.alicdn.com/kf/Hd581f8e1a43a41e2968cb6a8fe2c4084H.jpg"},{"Title":"进击的巨人 第二季","Href":"/detail/20170017","NewTitle":"[TV 01-12]","AID":"20170017","PicSmall":"https://sc04.alicdn.com/kf/Hc50377033ed746c9a5b84eaa500f1447X.jpg"},{"Title":"Fate/Apocrypha","Href":"/detail/20170055","NewTitle":"[TV 01-25]","AID":"20170055","PicSmall":"https://sc04.alicdn.com/kf/H062c07fc1b604943bd600343038ea934N.jpg"},{"Title":"动态漫画·传武","Href":"/detail/20210172","NewTitle":"第16集","AID":"20210172","PicSmall":"https://pic.rmb.bdstatic.com/bjh/081100befe90d51973a3812d95c5e5d2.jpeg"},{"Title":"战姬绝唱SYMPHOGEAR 第二季","Href":"/detail/20130093","NewTitle":"[TV 01-13 ]","AID":"20130093","PicSmall":"https://sc04.alicdn.com/kf/H7e907abe369343cabc5647e9a4e193ecG.jpg"},{"Title":"舞武器舞乱伎 第二季","Href":"/detail/20160137","NewTitle":"[TV 01-12]","AID":"20160137","PicSmall":"https://sc04.alicdn.com/kf/Hf40c1b314861464ab86ac4426adba8a1Y.jpg"},{"Title":"战姬绝唱SYMPHOGEAR 第五季","Href":"/detail/20190187","NewTitle":"[TV 01-13]","AID":"20190187","PicSmall":"https://sc04.alicdn.com/kf/H88998e431e9b4b1494702ba8261462cbI.jpg"},{"Title":"火影忍者 疾风传","Href":"/detail/20070037","NewTitle":"第720集(完结)","AID":"20070037","PicSmall":"https://sc04.alicdn.com/kf/Hd0da4b117af54daa95b4b8ee4a53a2a9T.jpg"}],"Tip":"AGE动漫网 备用地址：<a rel=\"nofollow\" target=\"_blank\" href=\"http://www.agefans.cc\" style=\"color: #60b8cc;text-decoration:  none;\">www.agefans.cc<\/a> 欢迎大家分享给身边朋友！为确保正常观看，请使用谷歌浏览器。","AniPreRel":[{"Title":"择天记","Href":"/detail/20150167","NewTitle":"第13集(完结)","AID":"20150167","PicSmall":"https://sc04.alicdn.com/kf/Hc770b229bec947299259de4fb5dcae14f.jpg"},{"Title":"择天记 第三季","Href":"/detail/20170245","NewTitle":"第12集(完结)","AID":"20170245","PicSmall":"https://sc04.alicdn.com/kf/H9b9ebf7942364e73afed5a7f238c7d35d.jpg"},{"Title":"择天记 第二季","Href":"/detail/20160236","NewTitle":"第12集(完结)","AID":"20160236","PicSmall":"https://sc04.alicdn.com/kf/H6caa9c2e8db64828a18733268c1597fbs.jpg"},{"Title":"择天记 第五季","Href":"/detail/20200154","NewTitle":"第12集(完结)","AID":"20200154","PicSmall":"https://sc04.alicdn.com/kf/H7fefe06ed624466c99629aeb0901e3b49.jpg"},{"Title":"择天记 第四季","Href":"/detail/20180348","NewTitle":"第12集(完结)","AID":"20180348","PicSmall":"https://sc04.alicdn.com/kf/Hcb7c236c4003482fb3917038e6a8f463Y.jpg"}],"AniInfo":{"CommentCnt":42,"R更新时间str2":"2019-03-17","R剧情类型2":["玄幻","热血","战斗"],"R简介":"各路敌手齐聚浔阳城，意欲袭击身受重伤的苏离，陈长生无视华介夫的劝告，决意拼死护卫为保护人族而负伤的苏离；陈长生在用燃剑、慧剑战梁王孙的同时，终于学会笨剑，成功抵挡肖张，但自此烧尽真元，失去战斗力，所幸王破出现，绝地反击肖张和梁王孙.......","R其它名称":"暂无","R地区":"中国","R在线播放":"","LastModified":"Sat, 19 Apr 2031 18:12:24 GMT","R更新时间str":"2019-03-17 15:01:36","R制作公司":"暂无","R标签2":["玄幻","热血","战斗"],"ModifiedTime":1618999944,"R标题V2":"","R首播季度":"10","R更新时间":"20190317150136","DEF_PLAYINDEX":"1","R在线播放3":"第01集 720P <play>PC-QPIC<\/play>qpic-20200154 择天记 第五季/择天记 第5季 第01集 720P nvl\r\n第02集 720P <play>PC-QPIC<\/play>qpic-20200154 择天记 第五季/择天记 第5季 第02集 720P nvl\r\n第03集 720P <play>PC-QPIC<\/play>qpic-20200154 择天记 第五季/择天记 第5季 第03集 720P nvl\r\n第04集 720P <play>PC-QPIC<\/play>qpic-20200154 择天记 第五季/择天记 第5季 第04集 720P nvl\r\n第05集 720P <play>PC-QPIC<\/play>qpic-20200154 择天记 第五季/择天记 第5季 第05集 720P nvl\r\n第06集 720P <play>PC-QPIC<\/play>qpic-20200154 择天记 第五季/择天记 第5季 第06集 720P nvl\r\n第07集 720P <play>PC-QPIC<\/play>qpic-20200154 择天记 第五季/择天记 第5季 第07集 720P nvl\r\n第08集 720P <play>PC-QPIC<\/play>qpic-20200154 择天记 第五季/择天记 第5季 第08集 720P nvl\r\n第09集 720P <play>PC-QPIC<\/play>qpic-20200154 择天记 第五季/择天记 第5季 第09集 720P nvl\r\n第10集 720P <play>PC-QPIC<\/play>qpic-20200154 择天记 第五季/择天记 第5季 第10集 720P nvl\r\n第11集 720P <play>PC-QPIC<\/play>qpic-20200154 择天记 第五季/择天记 第5季 第11集 720P nvl\r\n第12集 720P <play>PC-QPIC<\/play>qpic-20200154 择天记 第五季/择天记 第5季 第12集 720P nvl","R在线播放2":"第50话 <play>腾讯接口<\/play>//v.qq.com/x/cover/mzc002000he7xqq/c00338tua4q.html\r\n第51话 <play>腾讯接口<\/play>//v.qq.com/x/cover/mzc002000he7xqq/o0033yo182t.html\r\n第52话 <play>腾讯接口<\/play>//v.qq.com/x/cover/mzc002000he7xqq/j0033ysigbd.html\r\n第53话 <play>腾讯接口<\/play>//v.qq.com/x/cover/mzc002000he7xqq/m0033flrwi3.html\r\n第54话 <play>腾讯接口<\/play>//v.qq.com/x/cover/mzc002000he7xqq/v00333vta13.html\r\n第55话 <play>腾讯接口<\/play>//v.qq.com/x/cover/mzc002000he7xqq/d0033zyh3mp.html\r\n第56话 <play>腾讯接口<\/play>//v.qq.com/x/cover/mzc002000he7xqq/a0033cr0w4d.html\r\n第57话 <play>腾讯接口<\/play>//v.qq.com/x/cover/mzc002000he7xqq/j00336q51r3.html\r\n第58话 <play>腾讯接口<\/play>//v.qq.com/x/cover/mzc002000he7xqq/o00339zzk14.html\r\n第59话 <play>腾讯接口<\/play>//v.qq.com/x/cover/mzc002000he7xqq/d0033z32xfg.html\r\n第60话 <play>腾讯接口<\/play>//v.qq.com/x/cover/mzc002000he7xqq/t0034nuwr8y.html\r\n第61话 <play>腾讯接口<\/play>//v.qq.com/x/cover/mzc002000he7xqq/q0034sj5z9x.html","R封面图":"https://sc04.alicdn.com/kf/Hdbbd7147fb204ff8a073aaf0811711c6C.jpg","R在线播放4":"第01集 <play>web_m3u8<\/play>https%3a%2f%2fmhkuaibo%2ecom%2f20200316%2feh1d9996%2findex%2em3u8\r\n第02集 <play>web_m3u8<\/play>https%3a%2f%2fmhkuaibo%2ecom%2f20200316%2fK0qGWckx%2findex%2em3u8\r\n第03集 <play>web_m3u8<\/play>https%3a%2f%2fmhkuaibo%2ecom%2f20200323%2fQZ436AV7%2findex%2em3u8\r\n第04集 <play>web_m3u8<\/play>https%3a%2f%2fmahua%2dkb%2ecom%2f20200408%2fAASuTDpv%2findex%2em3u8\r\n第05集 <play>web_m3u8<\/play>https%3a%2f%2fmahua%2dkb%2ecom%2f20200407%2fRkmprIf0%2findex%2em3u8\r\n第06集 <play>web_m3u8<\/play>https%3a%2f%2fmahua%2dkb%2ecom%2f20200412%2fWZEUWy7g%2findex%2em3u8\r\n第07集 <play>web_m3u8<\/play>https%3a%2f%2fmahua%2dkb%2ecom%2f20200419%2fWQIvnq8n%2findex%2em3u8\r\n第08集 <play>web_m3u8<\/play>https%3a%2f%2fmahua%2dkb%2ecom%2f20200426%2fSEvLMWOG%2findex%2em3u8\r\n第09集 <play>web_m3u8<\/play>https%3a%2f%2fmahua%2dkb%2ecom%2f20200503%2fiOSKMIFy%2findex%2em3u8\r\n第10集 <play>web_m3u8<\/play>https%3a%2f%2fmahua%2dkb%2ecom%2f20200510%2fBIcfq7YF%2findex%2em3u8\r\n第11集 <play>web_m3u8<\/play>https%3a%2f%2fd%2emahua%2dkb%2ecom%2f20200517%2f2ztWX0T2%2findex%2em3u8\r\n第12集 <play>web_m3u8<\/play>https%3a%2f%2fd%2emahua%2dkb%2ecom%2f20200524%2fHW0OZqCz%2findex%2em3u8","AID":"20200154","R系列":"择天记","R播放状态":"完结","R备用":"","R原版名称":"择天记 第五季","R原作":"猫腻","R简介_br":"各路敌手齐聚浔阳城，意欲袭击身受重伤的苏离，陈长生无视华介夫的劝告，决意拼死护卫为保护人族而负伤的苏离；陈长生在用燃剑、慧剑战梁王孙的同时，终于学会笨剑，成功抵挡肖张，但自此烧尽真元，失去战斗力，所幸王破出现，绝地反击肖张和梁王孙.......","R在线播放All":[[],[{"PlayVid":"//v.qq.com/x/cover/mzc002000he7xqq/c00338tua4q.html","Ex":"","Title_l":"第50话","Title":"第50话","EpName":"50","PlayId":"<play>腾讯接口<\/play>","EpPic":""},{"PlayVid":"//v.qq.com/x/cover/mzc002000he7xqq/o0033yo182t.html","Ex":"","Title_l":"第51话","Title":"第51话","EpName":"51","PlayId":"<play>腾讯接口<\/play>","EpPic":""},{"PlayVid":"//v.qq.com/x/cover/mzc002000he7xqq/j0033ysigbd.html","Ex":"","Title_l":"第52话","Title":"第52话","EpName":"52","PlayId":"<play>腾讯接口<\/play>","EpPic":""},{"PlayVid":"//v.qq.com/x/cover/mzc002000he7xqq/m0033flrwi3.html","Ex":"","Title_l":"第53话","Title":"第53话","EpName":"53","PlayId":"<play>腾讯接口<\/play>","EpPic":""},{"PlayVid":"//v.qq.com/x/cover/mzc002000he7xqq/v00333vta13.html","Ex":"","Title_l":"第54话","Title":"第54话","EpName":"54","PlayId":"<play>腾讯接口<\/play>","EpPic":""},{"PlayVid":"//v.qq.com/x/cover/mzc002000he7xqq/d0033zyh3mp.html","Ex":"","Title_l":"第55话","Title":"第55话","EpName":"55","PlayId":"<play>腾讯接口<\/play>","EpPic":""},{"PlayVid":"//v.qq.com/x/cover/mzc002000he7xqq/a0033cr0w4d.html","Ex":"","Title_l":"第56话","Title":"第56话","EpName":"56","PlayId":"<play>腾讯接口<\/play>","EpPic":""},{"PlayVid":"//v.qq.com/x/cover/mzc002000he7xqq/j00336q51r3.html","Ex":"","Title_l":"第57话","Title":"第57话","EpName":"57","PlayId":"<play>腾讯接口<\/play>","EpPic":""},{"PlayVid":"//v.qq.com/x/cover/mzc002000he7xqq/o00339zzk14.html","Ex":"","Title_l":"第58话","Title":"第58话","EpName":"58","PlayId":"<play>腾讯接口<\/play>","EpPic":""},{"PlayVid":"//v.qq.com/x/cover/mzc002000he7xqq/d0033z32xfg.html","Ex":"","Title_l":"第59话","Title":"第59话","EpName":"59","PlayId":"<play>腾讯接口<\/play>","EpPic":""},{"PlayVid":"//v.qq.com/x/cover/mzc002000he7xqq/t0034nuwr8y.html","Ex":"","Title_l":"第60话","Title":"第60话","EpName":"60","PlayId":"<play>腾讯接口<\/play>","EpPic":""},{"PlayVid":"//v.qq.com/x/cover/mzc002000he7xqq/q0034sj5z9x.html","Ex":"","Title_l":"第61话","Title":"第61话","EpName":"61","PlayId":"<play>腾讯接口<\/play>","EpPic":""}],[{"PlayVid":"qpic-20200154 择天记 第五季/择天记 第5季 第01集 720P nvl","Ex":"","Title_l":"第01集 720P","Title":"第01集","EpName":"1","PlayId":"<play>PC-QPIC<\/play>","EpPic":""},{"PlayVid":"qpic-20200154 择天记 第五季/择天记 第5季 第02集 720P nvl","Ex":"","Title_l":"第02集 720P","Title":"第02集","EpName":"2","PlayId":"<play>PC-QPIC<\/play>","EpPic":""},{"PlayVid":"qpic-20200154 择天记 第五季/择天记 第5季 第03集 720P nvl","Ex":"","Title_l":"第03集 720P","Title":"第03集","EpName":"3","PlayId":"<play>PC-QPIC<\/play>","EpPic":""},{"PlayVid":"qpic-20200154 择天记 第五季/择天记 第5季 第04集 720P nvl","Ex":"","Title_l":"第04集 720P","Title":"第04集","EpName":"4","PlayId":"<play>PC-QPIC<\/play>","EpPic":""},{"PlayVid":"qpic-20200154 择天记 第五季/择天记 第5季 第05集 720P nvl","Ex":"","Title_l":"第05集 720P","Title":"第05集","EpName":"5","PlayId":"<play>PC-QPIC<\/play>","EpPic":""},{"PlayVid":"qpic-20200154 择天记 第五季/择天记 第5季 第06集 720P nvl","Ex":"","Title_l":"第06集 720P","Title":"第06集","EpName":"6","PlayId":"<play>PC-QPIC<\/play>","EpPic":""},{"PlayVid":"qpic-20200154 择天记 第五季/择天记 第5季 第07集 720P nvl","Ex":"","Title_l":"第07集 720P","Title":"第07集","EpName":"7","PlayId":"<play>PC-QPIC<\/play>","EpPic":""},{"PlayVid":"qpic-20200154 择天记 第五季/择天记 第5季 第08集 720P nvl","Ex":"","Title_l":"第08集 720P","Title":"第08集","EpName":"8","PlayId":"<play>PC-QPIC<\/play>","EpPic":""},{"PlayVid":"qpic-20200154 择天记 第五季/择天记 第5季 第09集 720P nvl","Ex":"","Title_l":"第09集 720P","Title":"第09集","EpName":"9","PlayId":"<play>PC-QPIC<\/play>","EpPic":""},{"PlayVid":"qpic-20200154 择天记 第五季/择天记 第5季 第10集 720P nvl","Ex":"","Title_l":"第10集 720P","Title":"第10集","EpName":"10","PlayId":"<play>PC-QPIC<\/play>","EpPic":""},{"PlayVid":"qpic-20200154 择天记 第五季/择天记 第5季 第11集 720P nvl","Ex":"","Title_l":"第11集 720P","Title":"第11集","EpName":"11","PlayId":"<play>PC-QPIC<\/play>","EpPic":""},{"PlayVid":"qpic-20200154 择天记 第五季/择天记 第5季 第12集 720P nvl","Ex":"","Title_l":"第12集 720P","Title":"第12集","EpName":"12","PlayId":"<play>PC-QPIC<\/play>","EpPic":""}],[{"PlayVid":"https%3a%2f%2fmhkuaibo%2ecom%2f20200316%2feh1d9996%2findex%2em3u8","Ex":"","Title_l":"第01集","Title":"第01集","EpName":"1","PlayId":"<play>web_m3u8<\/play>","EpPic":""},{"PlayVid":"https%3a%2f%2fmhkuaibo%2ecom%2f20200316%2fK0qGWckx%2findex%2em3u8","Ex":"","Title_l":"第02集","Title":"第02集","EpName":"2","PlayId":"<play>web_m3u8<\/play>","EpPic":""},{"PlayVid":"https%3a%2f%2fmhkuaibo%2ecom%2f20200323%2fQZ436AV7%2findex%2em3u8","Ex":"","Title_l":"第03集","Title":"第03集","EpName":"3","PlayId":"<play>web_m3u8<\/play>","EpPic":""},{"PlayVid":"https%3a%2f%2fmahua%2dkb%2ecom%2f20200408%2fAASuTDpv%2findex%2em3u8","Ex":"","Title_l":"第04集","Title":"第04集","EpName":"4","PlayId":"<play>web_m3u8<\/play>","EpPic":""},{"PlayVid":"https%3a%2f%2fmahua%2dkb%2ecom%2f20200407%2fRkmprIf0%2findex%2em3u8","Ex":"","Title_l":"第05集","Title":"第05集","EpName":"5","PlayId":"<play>web_m3u8<\/play>","EpPic":""},{"PlayVid":"https%3a%2f%2fmahua%2dkb%2ecom%2f20200412%2fWZEUWy7g%2findex%2em3u8","Ex":"","Title_l":"第06集","Title":"第06集","EpName":"6","PlayId":"<play>web_m3u8<\/play>","EpPic":""},{"PlayVid":"https%3a%2f%2fmahua%2dkb%2ecom%2f20200419%2fWQIvnq8n%2findex%2em3u8","Ex":"","Title_l":"第07集","Title":"第07集","EpName":"7","PlayId":"<play>web_m3u8<\/play>","EpPic":""},{"PlayVid":"https%3a%2f%2fmahua%2dkb%2ecom%2f20200426%2fSEvLMWOG%2findex%2em3u8","Ex":"","Title_l":"第08集","Title":"第08集","EpName":"8","PlayId":"<play>web_m3u8<\/play>","EpPic":""},{"PlayVid":"https%3a%2f%2fmahua%2dkb%2ecom%2f20200503%2fiOSKMIFy%2findex%2em3u8","Ex":"","Title_l":"第09集","Title":"第09集","EpName":"9","PlayId":"<play>web_m3u8<\/play>","EpPic":""},{"PlayVid":"https%3a%2f%2fmahua%2dkb%2ecom%2f20200510%2fBIcfq7YF%2findex%2em3u8","Ex":"","Title_l":"第10集","Title":"第10集","EpName":"10","PlayId":"<play>web_m3u8<\/play>","EpPic":""},{"PlayVid":"https%3a%2f%2fd%2emahua%2dkb%2ecom%2f20200517%2f2ztWX0T2%2findex%2em3u8","Ex":"","Title_l":"第11集","Title":"第11集","EpName":"11","PlayId":"<play>web_m3u8<\/play>","EpPic":""},{"PlayVid":"https%3a%2f%2fd%2emahua%2dkb%2ecom%2f20200524%2fHW0OZqCz%2findex%2em3u8","Ex":"","Title_l":"第12集","Title":"第12集","EpName":"12","PlayId":"<play>web_m3u8<\/play>","EpPic":""}]],"R资源类型":"","R标签":"玄幻 热血 战斗","R推荐星级":2,"R首播年份":"2020","R动画种类":"WEB","R官方网站":"暂无","R动画名称":"择天记 第五季","R更新时间unix":1552806096,"R剧情类型":"玄幻 热血 战斗","R字母索引":"Z","R网盘资源":"01-最新话\\n 链接：https://pan.baidu.com/s/1MnMMV0xny1Sg7dgWviy9-A 密码：7nuu\r\n\r\n01-最新话\\n https://quqi.gblhgk.com/s/1568700/bYwWsrWRf8mIbAOS","R视频尺寸":"720P/1080P","RankCnt":28070,"CollectCnt":47,"R首播时间":"2020","R网盘资源2":[{"Title":"01-最新话","ExCode":"7nuu","Link":"https://pan.baidu.com/s/1MnMMV0xny1Sg7dgWviy9-A"},{"Title":"01-最新话","ExCode":"","Link":"https://quqi.gblhgk.com/s/1568700/bYwWsrWRf8mIbAOS"}],"R封面图小":"https://sc04.alicdn.com/kf/H7fefe06ed624466c99629aeb0901e3b49.jpg","R新番标题":"第12集(完结)"}}