{"AniPreSim":[{"Title":"噬血狂袭 女武神的王国篇","Href":"/detail/20150063","NewTitle":"[OVA 01-02]","AID":"20150063","PicSmall":"https://sc04.alicdn.com/kf/H0db82f1d27da451898ea3ea5ae4179b4Q.jpg"},{"Title":"舞武器舞乱伎 第二季","Href":"/detail/20160137","NewTitle":"[TV 01-12]","AID":"20160137","PicSmall":"https://sc04.alicdn.com/kf/Hf40c1b314861464ab86ac4426adba8a1Y.jpg"},{"Title":"境界触发者 第二季","Href":"/detail/20200083","NewTitle":"第12集(完结)","AID":"20200083","PicSmall":"https://sc04.alicdn.com/kf/H58698161cf114df68afa33f11638e1d7N.jpg"},{"Title":"阴阳师·平安物语","Href":"/detail/20180322","NewTitle":"第12集(完结)","AID":"20180322","PicSmall":"https://sc04.alicdn.com/kf/H5350b0f71563409f9bbd9a14b0382bc7z.jpg"},{"Title":"你遭难了吗？","Href":"/detail/20190161","NewTitle":"[TV 01-12]","AID":"20190161","PicSmall":"https://sc04.alicdn.com/kf/Haa5457f482ff4572af9f16719ef2fd6bJ.jpg"},{"Title":"好比是最终迷宫前的少年到新手村生活一般的故事","Href":"/detail/20200013","NewTitle":"第12话(完结)","AID":"20200013","PicSmall":"https://sc04.alicdn.com/kf/Hcbb92175ff7445b081949e440977bf80f.jpg"},{"Title":"苍翼默示录 ALTER MEMORY","Href":"/detail/20130054","NewTitle":"[TV 01-12]","AID":"20130054","PicSmall":"https://sc04.alicdn.com/kf/Hb6d4ef5173724b0b82342c2f54d7b007x.jpg"},{"Title":"飞翔的魔女","Href":"/detail/20160063","NewTitle":"[TV 01-12+SP]","AID":"20160063","PicSmall":"https://sc04.alicdn.com/kf/H37c10bd0700741c9b6ab99f26884cf65W.jpg"}],"Tip":"AGE动漫网 备用地址：<a rel=\"nofollow\" target=\"_blank\" href=\"http://www.agefans.cc\" style=\"color: #60b8cc;text-decoration:  none;\">www.agefans.cc<\/a> 欢迎大家分享给身边朋友！为确保正常观看，请使用谷歌浏览器。","AniPreRel":[{"Title":"自称贤者弟子的贤者","Href":"/detail/20210155","NewTitle":"PV","AID":"20210155","PicSmall":"https://pic.rmb.bdstatic.com/bjh/a1ec34e96567b24bc785ec7358ccb628.jpeg"}],"AniInfo":{"CommentCnt":171,"R更新时间str2":"2021-03-26","R剧情类型2":["搞笑","奇幻","冒险"],"R简介":"电视动画《自称贤者弟子的贤者》改编自りゅうせんひろつぐ原作同名轻小说作品，于2020年5月宣布动画化的消息。\r\n在VRMMO游戏ArcEarthonline中，扮演九贤者之一，召唤师邓布鲁夫・冈达德亚一角的咲森鉴，突然在游戏的梦境中发生了逆转，跌落进了已经成为了现实的游戏世界中。\r\n而且，老练威严的贤者居然变成了楚楚可怜的少女。。。\r\n这样岂不是要让建立至今贤者的威严就此瓦解！\r\n想到这些的咲森鉴决定，用贤者弟子米拉的名义----------\r\n转生后的美少女冒险梦幻的金字塔，开幕！","R其它名称":"暂无","R地区":"日本","R在线播放":"PV1  <play>PC-QPIC<\/play>qpic-mup06/【2021年_大森日雅】自称贤者弟子的贤者 PV1【MCE汉化组】 720P nvl","LastModified":"Sat, 19 Apr 2031 18:12:38 GMT","R更新时间str":"2021-03-26 13:33:04","R制作公司":"暂无","R标签2":["搞笑","奇幻","冒险"],"ModifiedTime":1618999958,"R标题V2":"1","R首播季度":"10","R更新时间":"20210326133304","DEF_PLAYINDEX":"0","R在线播放3":"","R在线播放2":"","R封面图":"https://pic.rmb.bdstatic.com/bjh/f78e01d37366563f491e4baa02703a7d.jpeg","R在线播放4":"","AID":"20210155","R系列":"自称贤者弟子的贤者","R播放状态":"未播放","R备用":"","R原版名称":"賢者の弟子を名乗る賢者","R原作":"りゅうせんひろつぐ","R简介_br":"电视动画《自称贤者弟子的贤者》改编自りゅうせんひろつぐ原作同名轻小说作品，于2020年5月宣布动画化的消息。<br/>在VRMMO游戏ArcEarthonline中，扮演九贤者之一，召唤师邓布鲁夫・冈达德亚一角的咲森鉴，突然在游戏的梦境中发生了逆转，跌落进了已经成为了现实的游戏世界中。<br/>而且，老练威严的贤者居然变成了楚楚可怜的少女。。。<br/>这样岂不是要让建立至今贤者的威严就此瓦解！<br/>想到这些的咲森鉴决定，用贤者弟子米拉的名义----------<br/>转生后的美少女冒险梦幻的金字塔，开幕！","R在线播放All":[[{"PlayVid":"qpic-mup06/【2021年_大森日雅】自称贤者弟子的贤者 PV1【MCE汉化组】 720P nvl","Ex":"","Title_l":"PV1 ","Title":"PV1","EpName":"PV1","PlayId":"<play>PC-QPIC<\/play>","EpPic":""}],[],[],[]],"R资源类型":"","R标签":"搞笑 奇幻 冒险","R推荐星级":2,"R首播年份":"2021","R动画种类":"TV","R官方网站":"https://kendeshi-anime.com/","R动画名称":"自称贤者弟子的贤者","R更新时间unix":1616736784,"R剧情类型":"搞笑 奇幻 冒险","R字母索引":"Z","R网盘资源":"(暂缺)","R视频尺寸":"720P/1080P","RankCnt":14886,"CollectCnt":2241,"R首播时间":"2021","R网盘资源2":[],"R封面图小":"https://pic.rmb.bdstatic.com/bjh/a1ec34e96567b24bc785ec7358ccb628.jpeg","R新番标题":"PV"}}